Workbook

Sheet Sales Entry
B2: Sales Entry
B4: Date | C4: Invoice # | D4: Item / Service | E4: Category | F4: Qty | G4: Unit Price | H4: Total | I4: Payment Method | J4: Staff Name | K4: Customer Name | L4: Notes
H5: =IFERROR(F5*G5,0)
H6: =IFERROR(F6*G6,0)
H7: =IFERROR(F7*G7,0)
H8: =IFERROR(F8*G8,0)
H9: =IFERROR(F9*G9,0)
H10: =IFERROR(F10*G10,0)
H11: =IFERROR(F11*G11,0)
H12: =IFERROR(F12*G12,0)
H13: =IFERROR(F13*G13,0)
H14: =IFERROR(F14*G14,0)
H15: =IFERROR(F15*G15,0)
H16: =IFERROR(F16*G16,0)
... H304: =IFERROR(F304*G304,0)
B305: TOTALS | F305: =SUMPRODUCT((F5:F304)) | G305: =SUMPRODUCT((G5:G304)) | H305: =SUMPRODUCT((H5:H304))

Sheet Daily Summary
B2: Daily Summary
B4: Date | C4: Total Sales | D4: # Transactions | E4: Avg Transaction | F4: Cash Total | G4: Card Total | H4: Online Total | I4: # Items Sold
C5: =SUMPRODUCT(('Sales Entry'!$B$5:$B$304=B5)*('Sales Entry'!$H$5:$H$304)) | D5: =SUMPRODUCT(('Sales Entry'!$B$5:$B$304=B5)*1) | E5: =IFERROR(C5/D5,0) | F5: =SUMPRODUCT(('Sales Entry'!$B$5:$B$304=B5)*('Sales Entry'!$I$5:$I$304="Cash")*('Sales Entry'!$H$5:$H$304)) | G5: =SUMPRODUCT(('Sales Entry'!$B$5:$B$304=B5)*('Sales Entry'!$I$5:$I$304="Card")*('Sales Entry'!$H$5:$H$304)) | H5: =SUMPRODUCT(('Sales Entry'!$B$5:$B$304=B5)*('Sales Entry'!$I$5:$I$304="Online")*('Sales Entry'!$H$5:$H$304)) | I5: =SUMPRODUCT(('Sales Entry'!$B$5:$B$304=B5)*('Sales Entry'!$F$5:$F$304))
C6: =SUMPRODUCT(('Sales Entry'!$B$5:$B$304=B6)*('Sales Entry'!$H$5:$H$304)) | D6: =SUMPRODUCT(('Sales Entry'!$B$5:$B$304=B6)*1) | E6: =IFERROR(C6/D6,0) | F6: =SUMPRODUCT(('Sales Entry'!$B$5:$B$304=B6)*('Sales Entry'!$I$5:$I$304="Cash")*('Sales Entry'!$H$5:$H$304)) | G6: =SUMPRODUCT(('Sales Entry'!$B$5:$B$304=B6)*('Sales Entry'!$I$5:$I$304="Card")*('Sales Entry'!$H$5:$H$304)) | H6: =SUMPRODUCT(('Sales Entry'!$B$5:$B$304=B6)*('Sales Entry'!$I$5:$I$304="Online")*('Sales Entry'!$H$5:$H$304)) | I6: =SUMPRODUCT(('Sales Entry'!$B$5:$B$304=B6)*('Sales Entry'!$F$5:$F$304))
C7: =SUMPRODUCT(('Sales Entry'!$B$5:$B$304=B7)*('Sales Entry'!$H$5:$H$304)) | D7: =SUMPRODUCT(('Sales Entry'!$B$5:$B$304=B7)*1) | E7: =IFERROR(C7/D7,0) | F7: =SUMPRODUCT(('Sales Entry'!$B$5:$B$304=B7)*('Sales Entry'!$I$5:$I$304="Cash")*('Sales Entry'!$H$5:$H$304)) | G7: =SUMPRODUCT(('Sales Entry'!$B$5:$B$304=B7)*('Sales Entry'!$I$5:$I$304="Card")*('Sales Entry'!$H$5:$H$304)) | H7: =SUMPRODUCT(('Sales Entry'!$B$5:$B$304=B7)*('Sales Entry'!$I$5:$I$304="Online")*('Sales Entry'!$H$5:$H$304)) | I7: =SUMPRODUCT(('Sales Entry'!$B$5:$B$304=B7)*('Sales Entry'!$F$5:$F$304))
C8: =SUMPRODUCT(('Sales Entry'!$B$5:$B$304=B8)*('Sales Entry'!$H$5:$H$304)) | D8: =SUMPRODUCT(('Sales Entry'!$B$5:$B$304=B8)*1) | E8: =IFERROR(C8/D8,0) | F8: =SUMPRODUCT(('Sales Entry'!$B$5:$B$304=B8)*('Sales Entry'!$I$5:$I$304="Cash")*('Sales Entry'!$H$5:$H$304)) | G8: =SUMPRODUCT(('Sales Entry'!$B$5:$B$304=B8)*('Sales Entry'!$I$5:$I$304="Card")*('Sales Entry'!$H$5:$H$304)) | H8: =SUMPRODUCT(('Sales Entry'!$B$5:$B$304=B8)*('Sales Entry'!$I$5:$I$304="Online")*('Sales Entry'!$H$5:$H$304)) | I8: =SUMPRODUCT(('Sales Entry'!$B$5:$B$304=B8)*('Sales Entry'!$F$5:$F$304))
C9: =SUMPRODUCT(('Sales Entry'!$B$5:$B$304=B9)*('Sales Entry'!$H$5:$H$304)) | D9: =SUMPRODUCT(('Sales Entry'!$B$5:$B$304=B9)*1) | E9: =IFERROR(C9/D9,0) | F9: =SUMPRODUCT(('Sales Entry'!$B$5:$B$304=B9)*('Sales Entry'!$I$5:$I$304="Cash")*('Sales Entry'!$H$5:$H$304)) | G9: =SUMPRODUCT(('Sales Entry'!$B$5:$B$304=B9)*('Sales Entry'!$I$5:$I$304="Card")*('Sales Entry'!$H$5:$H$304)) | H9: =SUMPRODUCT(('Sales Entry'!$B$5:$B$304=B9)*('Sales Entry'!$I$5:$I$304="Online")*('Sales Entry'!$H$5:$H$304)) | I9: =SUMPRODUCT(('Sales Entry'!$B$5:$B$304=B9)*('Sales Entry'!$F$5:$F$304))
C10: =SUMPRODUCT(('Sales Entry'!$B$5:$B$304=B10)*('Sales Entry'!$H$5:$H$304)) | D10: =SUMPRODUCT(('Sales Entry'!$B$5:$B$304=B10)*1) | E10: =IFERROR(C10/D10,0) | F10: =SUMPRODUCT(('Sales Entry'!$B$5:$B$304=B10)*('Sales Entry'!$I$5:$I$304="Cash")*('Sales Entry'!$H$5:$H$304)) | G10: =SUMPRODUCT(('Sales Entry'!$B$5:$B$304=B10)*('Sales Entry'!$I$5:$I$304="Card")*('Sales Entry'!$H$5:$H$304)) | H10: =SUMPRODUCT(('Sales Entry'!$B$5:$B$304=B10)*('Sales Entry'!$I$5:$I$304="Online")*('Sales Entry'!$H$5:$H$304)) | I10: =SUMPRODUCT(('Sales Entry'!$B$5:$B$304=B10)*('Sales Entry'!$F$5:$F$304))
C11: =SUMPRODUCT(('Sales Entry'!$B$5:$B$304=B11)*('Sales Entry'!$H$5:$H$304)) | D11: =SUMPRODUCT(('Sales Entry'!$B$5:$B$304=B11)*1) | E11: =IFERROR(C11/D11,0) | F11: =SUMPRODUCT(('Sales Entry'!$B$5:$B$304=B11)*('Sales Entry'!$I$5:$I$304="Cash")*('Sales Entry'!$H$5:$H$304)) | G11: =SUMPRODUCT(('Sales Entry'!$B$5:$B$304=B11)*('Sales Entry'!$I$5:$I$304="Card")*('Sales Entry'!$H$5:$H$304)) | H11: =SUMPRODUCT(('Sales Entry'!$B$5:$B$304=B11)*('Sales Entry'!$I$5:$I$304="Online")*('Sales Entry'!$H$5:$H$304)) | I11: =SUMPRODUCT(('Sales Entry'!$B$5:$B$304=B11)*('Sales Entry'!$F$5:$F$304))
C12: =SUMPRODUCT(('Sales Entry'!$B$5:$B$304=B12)*('Sales Entry'!$H$5:$H$304)) | D12: =SUMPRODUCT(('Sales Entry'!$B$5:$B$304=B12)*1) | E12: =IFERROR(C12/D12,0) | F12: =SUMPRODUCT(('Sales Entry'!$B$5:$B$304=B12)*('Sales Entry'!$I$5:$I$304="Cash")*('Sales Entry'!$H$5:$H$304)) | G12: =SUMPRODUCT(('Sales Entry'!$B$5:$B$304=B12)*('Sales Entry'!$I$5:$I$304="Card")*('Sales Entry'!$H$5:$H$304)) | H12: =SUMPRODUCT(('Sales Entry'!$B$5:$B$304=B12)*('Sales Entry'!$I$5:$I$304="Online")*('Sales Entry'!$H$5:$H$304)) | I12: =SUMPRODUCT(('Sales Entry'!$B$5:$B$304=B12)*('Sales Entry'!$F$5:$F$304))
C13: =SUMPRODUCT(('Sales Entry'!$B$5:$B$304=B13)*('Sales Entry'!$H$5:$H$304)) | D13: =SUMPRODUCT(('Sales Entry'!$B$5:$B$304=B13)*1) | E13: =IFERROR(C13/D13,0) | F13: =SUMPRODUCT(('Sales Entry'!$B$5:$B$304=B13)*('Sales Entry'!$I$5:$I$304="Cash")*('Sales Entry'!$H$5:$H$304)) | G13: =SUMPRODUCT(('Sales Entry'!$B$5:$B$304=B13)*('Sales Entry'!$I$5:$I$304="Card")*('Sales Entry'!$H$5:$H$304)) | H13: =SUMPRODUCT(('Sales Entry'!$B$5:$B$304=B13)*('Sales Entry'!$I$5:$I$304="Online")*('Sales Entry'!$H$5:$H$304)) | I13: =SUMPRODUCT(('Sales Entry'!$B$5:$B$304=B13)*('Sales Entry'!$F$5:$F$304))
C14: =SUMPRODUCT(('Sales Entry'!$B$5:$B$304=B14)*('Sales Entry'!$H$5:$H$304)) | D14: =SUMPRODUCT(('Sales Entry'!$B$5:$B$304=B14)*1) | E14: =IFERROR(C14/D14,0) | F14: =SUMPRODUCT(('Sales Entry'!$B$5:$B$304=B14)*('Sales Entry'!$I$5:$I$304="Cash")*('Sales Entry'!$H$5:$H$304)) | G14: =SUMPRODUCT(('Sales Entry'!$B$5:$B$304=B14)*('Sales Entry'!$I$5:$I$304="Card")*('Sales Entry'!$H$5:$H$304)) | H14: =SUMPRODUCT(('Sales Entry'!$B$5:$B$304=B14)*('Sales Entry'!$I$5:$I$304="Online")*('Sales Entry'!$H$5:$H$304)) | I14: =SUMPRODUCT(('Sales Entry'!$B$5:$B$304=B14)*('Sales Entry'!$F$5:$F$304))
C15: =SUMPRODUCT(('Sales Entry'!$B$5:$B$304=B15)*('Sales Entry'!$H$5:$H$304)) | D15: =SUMPRODUCT(('Sales Entry'!$B$5:$B$304=B15)*1) | E15: =IFERROR(C15/D15,0) | F15: =SUMPRODUCT(('Sales Entry'!$B$5:$B$304=B15)*('Sales Entry'!$I$5:$I$304="Cash")*('Sales Entry'!$H$5:$H$304)) | G15: =SUMPRODUCT(('Sales Entry'!$B$5:$B$304=B15)*('Sales Entry'!$I$5:$I$304="Card")*('Sales Entry'!$H$5:$H$304)) | H15: =SUMPRODUCT(('Sales Entry'!$B$5:$B$304=B15)*('Sales Entry'!$I$5:$I$304="Online")*('Sales Entry'!$H$5:$H$304)) | I15: =SUMPRODUCT(('Sales Entry'!$B$5:$B$304=B15)*('Sales Entry'!$F$5:$F$304))
C16: =SUMPRODUCT(('Sales Entry'!$B$5:$B$304=B16)*('Sales Entry'!$H$5:$H$304)) | D16: =SUMPRODUCT(('Sales Entry'!$B$5:$B$304=B16)*1) | E16: =IFERROR(C16/D16,0) | F16: =SUMPRODUCT(('Sales Entry'!$B$5:$B$304=B16)*('Sales Entry'!$I$5:$I$304="Cash")*('Sales Entry'!$H$5:$H$304)) | G16: =SUMPRODUCT(('Sales Entry'!$B$5:$B$304=B16)*('Sales Entry'!$I$5:$I$304="Card")*('Sales Entry'!$H$5:$H$304)) | H16: =SUMPRODUCT(('Sales Entry'!$B$5:$B$304=B16)*('Sales Entry'!$I$5:$I$304="Online")*('Sales Entry'!$H$5:$H$304)) | I16: =SUMPRODUCT(('Sales Entry'!$B$5:$B$304=B16)*('Sales Entry'!$F$5:$F$304))
... C35: =SUMPRODUCT(('Sales Entry'!$B$5:$B$304=B35)*('Sales Entry'!$H$5:$H$304)) | D35: =SUMPRODUCT(('Sales Entry'!$B$5:$B$304=B35)*1) | E35: =IFERROR(C35/D35,0) | F35: =SUMPRODUCT(('Sales Entry'!$B$5:$B$304=B35)*('Sales Entry'!$I$5:$I$304="Cash")*('Sales Entry'!$H$5:$H$304)) | G35: =SUMPRODUCT(('Sales Entry'!$B$5:$B$304=B35)*('Sales Entry'!$I$5:$I$304="Card")*('Sales Entry'!$H$5:$H$304)) | H35: =SUMPRODUCT(('Sales Entry'!$B$5:$B$304=B35)*('Sales Entry'!$I$5:$I$304="Online")*('Sales Entry'!$H$5:$H$304)) | I35: =SUMPRODUCT(('Sales Entry'!$B$5:$B$304=B35)*('Sales Entry'!$F$5:$F$304))
B36: TOTALS | C36: =SUM(C5:C35) | D36: =SUM(D5:D35) | E36: =IFERROR(C36/D36,0) | F36: =SUM(F5:F35) | G36: =SUM(G5:G35) | H36: =SUM(H5:H35) | I36: =SUM(I5:I35)

Sheet Weekly Summary
B2: Weekly Summary
B4: Week # | C4: Week Start | D4: Week End | E4: Total Sales | F4: # Transactions | G4: Avg Transaction | H4: Top Staff
B5: 1 | E5: =SUMPRODUCT(('Daily Summary'!$B$5:$B$35>=C5)*('Daily Summary'!$B$5:$B$35<=D5)*('Daily Summary'!$C$5:$C$35)) | F5: =SUMPRODUCT(('Daily Summary'!$B$5:$B$35>=C5)*('Daily Summary'!$B$5:$B$35<=D5)*('Daily Summary'!$D$5:$D$35)) | G5: =IFERROR(E5/F5,0)
B6: 2 | E6: =SUMPRODUCT(('Daily Summary'!$B$5:$B$35>=C6)*('Daily Summary'!$B$5:$B$35<=D6)*('Daily Summary'!$C$5:$C$35)) | F6: =SUMPRODUCT(('Daily Summary'!$B$5:$B$35>=C6)*('Daily Summary'!$B$5:$B$35<=D6)*('Daily Summary'!$D$5:$D$35)) | G6: =IFERROR(E6/F6,0)
B7: 3 | E7: =SUMPRODUCT(('Daily Summary'!$B$5:$B$35>=C7)*('Daily Summary'!$B$5:$B$35<=D7)*('Daily Summary'!$C$5:$C$35)) | F7: =SUMPRODUCT(('Daily Summary'!$B$5:$B$35>=C7)*('Daily Summary'!$B$5:$B$35<=D7)*('Daily Summary'!$D$5:$D$35)) | G7: =IFERROR(E7/F7,0)
B8: 4 | E8: =SUMPRODUCT(('Daily Summary'!$B$5:$B$35>=C8)*('Daily Summary'!$B$5:$B$35<=D8)*('Daily Summary'!$C$5:$C$35)) | F8: =SUMPRODUCT(('Daily Summary'!$B$5:$B$35>=C8)*('Daily Summary'!$B$5:$B$35<=D8)*('Daily Summary'!$D$5:$D$35)) | G8: =IFERROR(E8/F8,0)
B9: 5 | E9: =SUMPRODUCT(('Daily Summary'!$B$5:$B$35>=C9)*('Daily Summary'!$B$5:$B$35<=D9)*('Daily Summary'!$C$5:$C$35)) | F9: =SUMPRODUCT(('Daily Summary'!$B$5:$B$35>=C9)*('Daily Summary'!$B$5:$B$35<=D9)*('Daily Summary'!$D$5:$D$35)) | G9: =IFERROR(E9/F9,0)
B10: 6 | E10: =SUMPRODUCT(('Daily Summary'!$B$5:$B$35>=C10)*('Daily Summary'!$B$5:$B$35<=D10)*('Daily Summary'!$C$5:$C$35)) | F10: =SUMPRODUCT(('Daily Summary'!$B$5:$B$35>=C10)*('Daily Summary'!$B$5:$B$35<=D10)*('Daily Summary'!$D$5:$D$35)) | G10: =IFERROR(E10/F10,0)
B11: 7 | E11: =SUMPRODUCT(('Daily Summary'!$B$5:$B$35>=C11)*('Daily Summary'!$B$5:$B$35<=D11)*('Daily Summary'!$C$5:$C$35)) | F11: =SUMPRODUCT(('Daily Summary'!$B$5:$B$35>=C11)*('Daily Summary'!$B$5:$B$35<=D11)*('Daily Summary'!$D$5:$D$35)) | G11: =IFERROR(E11/F11,0)
B12: 8 | E12: =SUMPRODUCT(('Daily Summary'!$B$5:$B$35>=C12)*('Daily Summary'!$B$5:$B$35<=D12)*('Daily Summary'!$C$5:$C$35)) | F12: =SUMPRODUCT(('Daily Summary'!$B$5:$B$35>=C12)*('Daily Summary'!$B$5:$B$35<=D12)*('Daily Summary'!$D$5:$D$35)) | G12: =IFERROR(E12/F12,0)
B13: 9 | E13: =SUMPRODUCT(('Daily Summary'!$B$5:$B$35>=C13)*('Daily Summary'!$B$5:$B$35<=D13)*('Daily Summary'!$C$5:$C$35)) | F13: =SUMPRODUCT(('Daily Summary'!$B$5:$B$35>=C13)*('Daily Summary'!$B$5:$B$35<=D13)*('Daily Summary'!$D$5:$D$35)) | G13: =IFERROR(E13/F13,0)
B14: 10 | E14: =SUMPRODUCT(('Daily Summary'!$B$5:$B$35>=C14)*('Daily Summary'!$B$5:$B$35<=D14)*('Daily Summary'!$C$5:$C$35)) | F14: =SUMPRODUCT(('Daily Summary'!$B$5:$B$35>=C14)*('Daily Summary'!$B$5:$B$35<=D14)*('Daily Summary'!$D$5:$D$35)) | G14: =IFERROR(E14/F14,0)
B15: 11 | E15: =SUMPRODUCT(('Daily Summary'!$B$5:$B$35>=C15)*('Daily Summary'!$B$5:$B$35<=D15)*('Daily Summary'!$C$5:$C$35)) | F15: =SUMPRODUCT(('Daily Summary'!$B$5:$B$35>=C15)*('Daily Summary'!$B$5:$B$35<=D15)*('Daily Summary'!$D$5:$D$35)) | G15: =IFERROR(E15/F15,0)
B16: 12 | E16: =SUMPRODUCT(('Daily Summary'!$B$5:$B$35>=C16)*('Daily Summary'!$B$5:$B$35<=D16)*('Daily Summary'!$C$5:$C$35)) | F16: =SUMPRODUCT(('Daily Summary'!$B$5:$B$35>=C16)*('Daily Summary'!$B$5:$B$35<=D16)*('Daily Summary'!$D$5:$D$35)) | G16: =IFERROR(E16/F16,0)
... B56: 52 | E56: =SUMPRODUCT(('Daily Summary'!$B$5:$B$35>=C56)*('Daily Summary'!$B$5:$B$35<=D56)*('Daily Summary'!$C$5:$C$35)) | F56: =SUMPRODUCT(('Daily Summary'!$B$5:$B$35>=C56)*('Daily Summary'!$B$5:$B$35<=D56)*('Daily Summary'!$D$5:$D$35)) | G56: =IFERROR(E56/F56,0)
B57: TOTALS | E57: =SUM(E5:E56) | F57: =SUM(F5:F56) | G57: =IFERROR(E57/F57,0)

Sheet Monthly Summary
B2: Monthly Summary
B4: Month | C4: Total Sales | D4: # Transactions | E4: Avg Transaction | F4: Best Day Sales | G4: Best Day Date
B5: January | C5: =SUMPRODUCT((MONTH('Daily Summary'!$B$5:$B$35)=1)*('Daily Summary'!$C$5:$C$35)) | D5: =SUMPRODUCT((MONTH('Daily Summary'!$B$5:$B$35)=1)*('Daily Summary'!$D$5:$D$35)) | E5: =IFERROR(C5/D5,0) | F5: =MAX(IF(MONTH('Daily Summary'!$B$5:$B$35)=1,'Daily Summary'!$C$5:$C$35))
B6: February | C6: =SUMPRODUCT((MONTH('Daily Summary'!$B$5:$B$35)=2)*('Daily Summary'!$C$5:$C$35)) | D6: =SUMPRODUCT((MONTH('Daily Summary'!$B$5:$B$35)=2)*('Daily Summary'!$D$5:$D$35)) | E6: =IFERROR(C6/D6,0) | F6: =MAX(IF(MONTH('Daily Summary'!$B$5:$B$35)=2,'Daily Summary'!$C$5:$C$35))
B7: March | C7: =SUMPRODUCT((MONTH('Daily Summary'!$B$5:$B$35)=3)*('Daily Summary'!$C$5:$C$35)) | D7: =SUMPRODUCT((MONTH('Daily Summary'!$B$5:$B$35)=3)*('Daily Summary'!$D$5:$D$35)) | E7: =IFERROR(C7/D7,0) | F7: =MAX(IF(MONTH('Daily Summary'!$B$5:$B$35)=3,'Daily Summary'!$C$5:$C$35))
B8: April | C8: =SUMPRODUCT((MONTH('Daily Summary'!$B$5:$B$35)=4)*('Daily Summary'!$C$5:$C$35)) | D8: =SUMPRODUCT((MONTH('Daily Summary'!$B$5:$B$35)=4)*('Daily Summary'!$D$5:$D$35)) | E8: =IFERROR(C8/D8,0) | F8: =MAX(IF(MONTH('Daily Summary'!$B$5:$B$35)=4,'Daily Summary'!$C$5:$C$35))
B9: May | C9: =SUMPRODUCT((MONTH('Daily Summary'!$B$5:$B$35)=5)*('Daily Summary'!$C$5:$C$35)) | D9: =SUMPRODUCT((MONTH('Daily Summary'!$B$5:$B$35)=5)*('Daily Summary'!$D$5:$D$35)) | E9: =IFERROR(C9/D9,0) | F9: =MAX(IF(MONTH('Daily Summary'!$B$5:$B$35)=5,'Daily Summary'!$C$5:$C$35))
B10: June | C10: =SUMPRODUCT((MONTH('Daily Summary'!$B$5:$B$35)=6)*('Daily Summary'!$C$5:$C$35)) | D10: =SUMPRODUCT((MONTH('Daily Summary'!$B$5:$B$35)=6)*('Daily Summary'!$D$5:$D$35)) | E10: =IFERROR(C10/D10,0) | F10: =MAX(IF(MONTH('Daily Summary'!$B$5:$B$35)=6,'Daily Summary'!$C$5:$C$35))
B11: July | C11: =SUMPRODUCT((MONTH('Daily Summary'!$B$5:$B$35)=7)*('Daily Summary'!$C$5:$C$35)) | D11: =SUMPRODUCT((MONTH('Daily Summary'!$B$5:$B$35)=7)*('Daily Summary'!$D$5:$D$35)) | E11: =IFERROR(C11/D11,0) | F11: =MAX(IF(MONTH('Daily Summary'!$B$5:$B$35)=7,'Daily Summary'!$C$5:$C$35))
B12: August | C12: =SUMPRODUCT((MONTH('Daily Summary'!$B$5:$B$35)=8)*('Daily Summary'!$C$5:$C$35)) | D12: =SUMPRODUCT((MONTH('Daily Summary'!$B$5:$B$35)=8)*('Daily Summary'!$D$5:$D$35)) | E12: =IFERROR(C12/D12,0) | F12: =MAX(IF(MONTH('Daily Summary'!$B$5:$B$35)=8,'Daily Summary'!$C$5:$C$35))
B13: September | C13: =SUMPRODUCT((MONTH('Daily Summary'!$B$5:$B$35)=9)*('Daily Summary'!$C$5:$C$35)) | D13: =SUMPRODUCT((MONTH('Daily Summary'!$B$5:$B$35)=9)*('Daily Summary'!$D$5:$D$35)) | E13: =IFERROR(C13/D13,0) | F13: =MAX(IF(MONTH('Daily Summary'!$B$5:$B$35)=9,'Daily Summary'!$C$5:$C$35))
B14: October | C14: =SUMPRODUCT((MONTH('Daily Summary'!$B$5:$B$35)=10)*('Daily Summary'!$C$5:$C$35)) | D14: =SUMPRODUCT((MONTH('Daily Summary'!$B$5:$B$35)=10)*('Daily Summary'!$D$5:$D$35)) | E14: =IFERROR(C14/D14,0) | F14: =MAX(IF(MONTH('Daily Summary'!$B$5:$B$35)=10,'Daily Summary'!$C$5:$C$35))
B15: November | C15: =SUMPRODUCT((MONTH('Daily Summary'!$B$5:$B$35)=11)*('Daily Summary'!$C$5:$C$35)) | D15: =SUMPRODUCT((MONTH('Daily Summary'!$B$5:$B$35)=11)*('Daily Summary'!$D$5:$D$35)) | E15: =IFERROR(C15/D15,0) | F15: =MAX(IF(MONTH('Daily Summary'!$B$5:$B$35)=11,'Daily Summary'!$C$5:$C$35))
B16: December | C16: =SUMPRODUCT((MONTH('Daily Summary'!$B$5:$B$35)=12)*('Daily Summary'!$C$5:$C$35)) | D16: =SUMPRODUCT((MONTH('Daily Summary'!$B$5:$B$35)=12)*('Daily Summary'!$D$5:$D$35)) | E16: =IFERROR(C16/D16,0) | F16: =MAX(IF(MONTH('Daily Summary'!$B$5:$B$35)=12,'Daily Summary'!$C$5:$C$35))
B17: TOTALS | C17: =SUM(C5:C16) | D17: =SUM(D5:D16) | E17: =IFERROR(C17/D17,0)

Sheet Invoice
B2: YOUR COMPANY NAME
B3: Address Line | Phone | Email | Website
B5: Invoice #: | E5: Date:
B6: Customer: | E6: Staff:
B8: Item | C8: Qty | D8: Price | E8: Total
E9: =IFERROR(C9*D9,0)
E10: =IFERROR(C10*D10,0)
E11: =IFERROR(C11*D11,0)
E12: =IFERROR(C12*D12,0)
E13: =IFERROR(C13*D13,0)
E14: =IFERROR(C14*D14,0)
E15: =IFERROR(C15*D15,0)
E16: =IFERROR(C16*D16,0)
E17: =IFERROR(C17*D17,0)
E18: =IFERROR(C18*D18,0)
B19: Subtotal | E19: =SUM(E9:E18)
B20: VAT 5% | E20: =IFERROR(E19*0.05,0)
B21: Discount
B22: GRAND TOTAL | E22: =IFERROR(E19+E20-E21,0)
B24: Thank you for your business!

Sheet Inventory
B2: Inventory
B4: Product ID | C4: Item Name | D4: Category | E4: Unit Price | F4: Stock Qty | G4: Reorder Level | H4: Status | I4: Supplier | J4: Last Restocked
H5: =IF(F5<=G5,"LOW STOCK","In Stock")
H6: =IF(F6<=G6,"LOW STOCK","In Stock")
H7: =IF(F7<=G7,"LOW STOCK","In Stock")
H8: =IF(F8<=G8,"LOW STOCK","In Stock")
H9: =IF(F9<=G9,"LOW STOCK","In Stock")
H10: =IF(F10<=G10,"LOW STOCK","In Stock")
H11: =IF(F11<=G11,"LOW STOCK","In Stock")
H12: =IF(F12<=G12,"LOW STOCK","In Stock")
H13: =IF(F13<=G13,"LOW STOCK","In Stock")
H14: =IF(F14<=G14,"LOW STOCK","In Stock")
H15: =IF(F15<=G15,"LOW STOCK","In Stock")
H16: =IF(F16<=G16,"LOW STOCK","In Stock")
... H154: =IF(F154<=G154,"LOW STOCK","In Stock")
B155: SUMMARY | E155: =SUM(E5:E154) | G155: =SUM(G5:G154)

Sheet Staff Performance
B2: Staff Performance
B4: Staff Name | C4: Total Sales | D4: # Transactions | E4: Avg Transaction | F4: Top Category | G4: Shift | H4: Commission (5%)
C5: =SUMPRODUCT(('Sales Entry'!$J$5:$J$304=B5)*('Sales Entry'!$H$5:$H$304)) | D5: =SUMPRODUCT(('Sales Entry'!$J$5:$J$304=B5)*1) | E5: =IFERROR(C5/D5,0) | H5: =IFERROR(C5*0.05,0)
C6: =SUMPRODUCT(('Sales Entry'!$J$5:$J$304=B6)*('Sales Entry'!$H$5:$H$304)) | D6: =SUMPRODUCT(('Sales Entry'!$J$5:$J$304=B6)*1) | E6: =IFERROR(C6/D6,0) | H6: =IFERROR(C6*0.05,0)
C7: =SUMPRODUCT(('Sales Entry'!$J$5:$J$304=B7)*('Sales Entry'!$H$5:$H$304)) | D7: =SUMPRODUCT(('Sales Entry'!$J$5:$J$304=B7)*1) | E7: =IFERROR(C7/D7,0) | H7: =IFERROR(C7*0.05,0)
C8: =SUMPRODUCT(('Sales Entry'!$J$5:$J$304=B8)*('Sales Entry'!$H$5:$H$304)) | D8: =SUMPRODUCT(('Sales Entry'!$J$5:$J$304=B8)*1) | E8: =IFERROR(C8/D8,0) | H8: =IFERROR(C8*0.05,0)
C9: =SUMPRODUCT(('Sales Entry'!$J$5:$J$304=B9)*('Sales Entry'!$H$5:$H$304)) | D9: =SUMPRODUCT(('Sales Entry'!$J$5:$J$304=B9)*1) | E9: =IFERROR(C9/D9,0) | H9: =IFERROR(C9*0.05,0)
C10: =SUMPRODUCT(('Sales Entry'!$J$5:$J$304=B10)*('Sales Entry'!$H$5:$H$304)) | D10: =SUMPRODUCT(('Sales Entry'!$J$5:$J$304=B10)*1) | E10: =IFERROR(C10/D10,0) | H10: =IFERROR(C10*0.05,0)
C11: =SUMPRODUCT(('Sales Entry'!$J$5:$J$304=B11)*('Sales Entry'!$H$5:$H$304)) | D11: =SUMPRODUCT(('Sales Entry'!$J$5:$J$304=B11)*1) | E11: =IFERROR(C11/D11,0) | H11: =IFERROR(C11*0.05,0)
C12: =SUMPRODUCT(('Sales Entry'!$J$5:$J$304=B12)*('Sales Entry'!$H$5:$H$304)) | D12: =SUMPRODUCT(('Sales Entry'!$J$5:$J$304=B12)*1) | E12: =IFERROR(C12/D12,0) | H12: =IFERROR(C12*0.05,0)
C13: =SUMPRODUCT(('Sales Entry'!$J$5:$J$304=B13)*('Sales Entry'!$H$5:$H$304)) | D13: =SUMPRODUCT(('Sales Entry'!$J$5:$J$304=B13)*1) | E13: =IFERROR(C13/D13,0) | H13: =IFERROR(C13*0.05,0)
C14: =SUMPRODUCT(('Sales Entry'!$J$5:$J$304=B14)*('Sales Entry'!$H$5:$H$304)) | D14: =SUMPRODUCT(('Sales Entry'!$J$5:$J$304=B14)*1) | E14: =IFERROR(C14/D14,0) | H14: =IFERROR(C14*0.05,0)
C15: =SUMPRODUCT(('Sales Entry'!$J$5:$J$304=B15)*('Sales Entry'!$H$5:$H$304)) | D15: =SUMPRODUCT(('Sales Entry'!$J$5:$J$304=B15)*1) | E15: =IFERROR(C15/D15,0) | H15: =IFERROR(C15*0.05,0)
C16: =SUMPRODUCT(('Sales Entry'!$J$5:$J$304=B16)*('Sales Entry'!$H$5:$H$304)) | D16: =SUMPRODUCT(('Sales Entry'!$J$5:$J$304=B16)*1) | E16: =IFERROR(C16/D16,0) | H16: =IFERROR(C16*0.05,0)
... C24: =SUMPRODUCT(('Sales Entry'!$J$5:$J$304=B24)*('Sales Entry'!$H$5:$H$304)) | D24: =SUMPRODUCT(('Sales Entry'!$J$5:$J$304=B24)*1) | E24: =IFERROR(C24/D24,0) | H24: =IFERROR(C24*0.05,0)
B25: TOTALS | C25: =SUM(C5:C24) | D25: =SUM(D5:D24) | E25: =IFERROR(C25/D25,0) | H25: =SUM(H5:H24)

Sheet Product List
B2: Product List
B4: Product ID | C4: Item Name | D4: Category | E4: Unit Price | F4: Cost Price | G4: Margin % | H4: Description | I4: Supplier
G5: =IFERROR((E5-F5)/E5,0)
G6: =IFERROR((E6-F6)/E6,0)
G7: =IFERROR((E7-F7)/E7,0)
G8: =IFERROR((E8-F8)/E8,0)
G9: =IFERROR((E9-F9)/E9,0)
G10: =IFERROR((E10-F10)/E10,0)
G11: =IFERROR((E11-F11)/E11,0)
G12: =IFERROR((E12-F12)/E12,0)
G13: =IFERROR((E13-F13)/E13,0)
G14: =IFERROR((E14-F14)/E14,0)
G15: =IFERROR((E15-F15)/E15,0)
G16: =IFERROR((E16-F16)/E16,0)
... G204: =IFERROR((E204-F204)/E204,0)
B205: SUMMARY | E205: =IFERROR(SUM(E5:E204),0) | F205: =IFERROR(SUM(F5:F204),0) | G205: =IFERROR((E205-F205)/E205,0)
