Workbook

Sheet Dashboard
B2: TechZone Electronics — POS Dashboard
B3: March 2025 | Premium POS Report
B5: Total Revenue | D5: Total Expenses | F5: Net Profit | H5: Profit Margin % | J5: # Transactions | L5: Avg Transaction
B6: ='Monthly Summary'!C5 | D6: ='Monthly Summary'!G5 | F6: ='Profit Analysis'!C11 | H6: ='Profit Analysis'!C12 | J6: ='Monthly Summary'!D5 | L6: ='Monthly Summary'!E5
B50: Date | C50: Daily Sales
B51: 45717 | C51: ='Daily Summary'!C5
B52: 45718 | C52: ='Daily Summary'!C6
B53: 45719 | C53: ='Daily Summary'!C7
B54: 45720 | C54: ='Daily Summary'!C8
B55: 45721 | C55: ='Daily Summary'!C9
B56: 45722 | C56: ='Daily Summary'!C10
B57: 45723 | C57: ='Daily Summary'!C11
B58: 45724 | C58: ='Daily Summary'!C12
B59: 45725 | C59: ='Daily Summary'!C13
B60: 45726 | C60: ='Daily Summary'!C14
B61: 45727 | C61: ='Daily Summary'!C15
B62: 45728 | C62: ='Daily Summary'!C16
... B81: 45747 | C81: ='Daily Summary'!C35
B85: Category | C85: Amount
B86: Rent | C86: =SUMPRODUCT(('Expenses'!C5:C44=B86)*('Expenses'!E5:E44))
B87: Salaries | C87: =SUMPRODUCT(('Expenses'!C5:C44=B87)*('Expenses'!E5:E44))
B88: Utilities | C88: =SUMPRODUCT(('Expenses'!C5:C44=B88)*('Expenses'!E5:E44))
B89: Supplies | C89: =SUMPRODUCT(('Expenses'!C5:C44=B89)*('Expenses'!E5:E44))
B90: Maintenance | C90: =SUMPRODUCT(('Expenses'!C5:C44=B90)*('Expenses'!E5:E44))
B91: Marketing | C91: =SUMPRODUCT(('Expenses'!C5:C44=B91)*('Expenses'!E5:E44))
B92: Transport | C92: =SUMPRODUCT(('Expenses'!C5:C44=B92)*('Expenses'!E5:E44))
B93: Insurance | C93: =SUMPRODUCT(('Expenses'!C5:C44=B93)*('Expenses'!E5:E44))
B94: Miscellaneous | C94: =SUMPRODUCT(('Expenses'!C5:C44=B94)*('Expenses'!E5:E44))
B100: Staff | C100: Total Sales | D100: Target
B101: Ahmed | C101: ='Staff Performance'!C5 | D101: ='Staff Performance'!I5
B102: Fatima | C102: ='Staff Performance'!C6 | D102: ='Staff Performance'!I6
B103: Omar | C103: ='Staff Performance'!C7 | D103: ='Staff Performance'!I7
B104: Sara | C104: ='Staff Performance'!C8 | D104: ='Staff Performance'!I8
B105: Khalid | C105: ='Staff Performance'!C9 | D105: ='Staff Performance'!I9
B106: Maryam | C106: ='Staff Performance'!C10 | D106: ='Staff Performance'!I10
B115: Category | C115: Total Sales
B116: Accessories | C116: =SUMPRODUCT(('Sales Entry'!E5:E131=B116)*('Sales Entry'!M5:M131))
B117: Audio | C117: =SUMPRODUCT(('Sales Entry'!E5:E131=B117)*('Sales Entry'!M5:M131))
B118: Cables | C118: =SUMPRODUCT(('Sales Entry'!E5:E131=B118)*('Sales Entry'!M5:M131))
B119: Devices | C119: =SUMPRODUCT(('Sales Entry'!E5:E131=B119)*('Sales Entry'!M5:M131))
B120: Peripherals | C120: =SUMPRODUCT(('Sales Entry'!E5:E131=B120)*('Sales Entry'!M5:M131))
B121: Storage | C121: =SUMPRODUCT(('Sales Entry'!E5:E131=B121)*('Sales Entry'!M5:M131))
B122: Wearables | C122: =SUMPRODUCT(('Sales Entry'!E5:E131=B122)*('Sales Entry'!M5:M131))

Sheet Sales Entry
B2: Sales Entry — TechZone Electronics
B4: Date | C4: Invoice # | D4: Item/Service | E4: Category | F4: Qty | G4: Unit Price | H4: Total | I4: Payment Method | J4: Staff Name | K4: Customer Name | L4: Discount | M4: Net Total | N4: Notes
B5: 45717 | C5: INV-0101 | D5: Tablet | E5: Devices | F5: 1 | G5: 899 | H5: 899 | I5: Online | J5: Fatima | K5: Noor Al Hashmi | L5: 10 | M5: 889 | N5: Promo discount AED 10
B6: 45717 | C6: INV-0102 | D6: Bluetooth Speaker | E6: Audio | F6: 4 | G6: 150 | H6: 600 | I6: Cash | J6: Ahmed | K6: Youssef Al Mansoori | L6: 30 | M6: 570 | N6: Promo discount AED 30
B7: 45717 | C7: INV-0103 | D7: USB Cable | E7: Accessories | F7: 2 | G7: 25 | H7: 50 | I7: Online | J7: Maryam | K7: Walk-in | L7: 0 | M7: 50
B8: 45717 | C8: INV-0104 | D8: Adapter Plug | E8: Accessories | F8: 3 | G8: 20 | H8: 60 | I8: Online | J8: Ahmed | K8: Layla Al Qasimi | L8: 0 | M8: 60
B9: 45717 | C9: INV-0105 | D9: Monitor Cable | E9: Cables | F9: 3 | G9: 40 | H9: 120 | I9: Cash | J9: Omar | K9: Fatma Al Suwaidi | L9: 10 | M9: 110 | N9: Promo discount AED 10
B10: 45718 | C10: INV-0106 | D10: Phone Holder | E10: Accessories | F10: 3 | G10: 35 | H10: 105 | I10: Online | J10: Maryam | K10: Rashid Al Zaabi | L10: 0 | M10: 105
B11: 45718 | C11: INV-0107 | D11: Car Mount | E11: Accessories | F11: 1 | G11: 50 | H11: 50 | I11: Card | J11: Maryam | K11: Walk-in | L11: 0 | M11: 50
B12: 45718 | C12: INV-0108 | D12: Stylus Pen | E12: Accessories | F12: 2 | G12: 65 | H12: 130 | I12: Online | J12: Ahmed | K12: Noor Al Hashmi | L12: 0 | M12: 130
B13: 45718 | C13: INV-0109 | D13: Bluetooth Speaker | E13: Audio | F13: 2 | G13: 150 | H13: 300 | I13: Online | J13: Sara | K13: Saeed Al Dhaheri | L13: 0 | M13: 300
B14: 45719 | C14: INV-0110 | D14: Laptop Stand | E14: Accessories | F14: 3 | G14: 150 | H14: 450 | I14: Card | J14: Maryam | K14: Saeed Al Dhaheri | L14: 0 | M14: 450
B15: 45719 | C15: INV-0111 | D15: Earbuds | E15: Audio | F15: 2 | G15: 85 | H15: 170 | I15: Card | J15: Fatima | K15: Layla Al Qasimi | L15: 0 | M15: 170
B16: 45719 | C16: INV-0112 | D16: Memory Card 64GB | E16: Storage | F16: 2 | G16: 45 | H16: 90 | I16: Card | J16: Ahmed | K16: Noor Al Hashmi | L16: 0 | M16: 90
B17: 45719 | C17: INV-0113 | D17: Webcam | E17: Peripherals | F17: 4 | G17: 180 | H17: 720 | I17: Card | J17: Fatima | K17: Walk-in | L17: 0 | M17: 720
B18: 45720 | C18: INV-0114 | D18: Charger | E18: Accessories | F18: 4 | G18: 55 | H18: 220 | I18: Card | J18: Maryam | K18: Rashid Al Zaabi | L18: 15 | M18: 205 | N18: Promo discount AED 15
B19: 45720 | C19: INV-0115 | D19: Type-C Hub | E19: Accessories | F19: 3 | G19: 95 | H19: 285 | I19: Online | J19: Sara | K19: Walk-in | L19: 0 | M19: 285
B20: 45720 | C20: INV-0116 | D20: HDMI Cable | E20: Cables | F20: 2 | G20: 35 | H20: 70 | I20: Card | J20: Ahmed | K20: Aisha Al Maktoum | L20: 0 | M20: 70
B21: 45720 | C21: INV-0117 | D21: Fitness Band | E21: Wearables | F21: 2 | G21: 180 | H21: 360 | I21: Online | J21: Sara | K21: Walk-in | L21: 25 | M21: 335 | N21: Promo discount AED 25
B22: 45721 | C22: INV-0118 | D22: AV Cable | E22: Cables | F22: 3 | G22: 28 | H22: 84 | I22: Bank Transfer | J22: Ahmed | K22: Fatma Al Suwaidi | L22: 0 | M22: 84
B23: 45721 | C23: INV-0119 | D23: Memory Card 64GB | E23: Storage | F23: 3 | G23: 45 | H23: 135 | I23: Cash | J23: Sara | K23: Layla Al Qasimi | L23: 0 | M23: 135
B24: 45721 | C24: INV-0120 | D24: Wireless Charger | E24: Accessories | F24: 2 | G24: 110 | H24: 220 | I24: Card | J24: Ahmed | K24: Walk-in | L24: 40 | M24: 180 | N24: Promo discount AED 40
B25: 45721 | C25: INV-0121 | D25: Ring Light | E25: Accessories | F25: 2 | G25: 120 | H25: 240 | I25: Cash | J25: Fatima | K25: Walk-in | L25: 0 | M25: 240
B26: 45721 | C26: INV-0122 | D26: Tripod Stand | E26: Accessories | F26: 1 | G26: 90 | H26: 90 | I26: Card | J26: Sara | K26: Mohamed Al Rashid | L26: 20 | M26: 70 | N26: Promo discount AED 20
B27: 45722 | C27: INV-0123 | D27: Type-C Hub | E27: Accessories | F27: 1 | G27: 95 | H27: 95 | I27: Cash | J27: Khalid | K27: Hassan Al Nuaimi | L27: 25 | M27: 70 | N27: Promo discount AED 25
B28: 45722 | C28: INV-0124 | D28: Earbuds | E28: Audio | F28: 2 | G28: 85 | H28: 170 | I28: Cash | J28: Sara | K28: Walk-in | L28: 30 | M28: 140 | N28: Promo discount AED 30
B29: 45722 | C29: INV-0125 | D29: Mouse Pad XL | E29: Peripherals | F29: 2 | G29: 40 | H29: 80 | I29: Bank Transfer | J29: Maryam | K29: Youssef Al Mansoori | L29: 0 | M29: 80
B30: 45722 | C30: INV-0126 | D30: Surge Protector | E30: Accessories | F30: 3 | G30: 75 | H30: 225 | I30: Card | J30: Khalid | K30: Rashid Al Zaabi | L30: 15 | M30: 210 | N30: Promo discount AED 15
B31: 45723 | C31: INV-0127 | D31: Monitor Cable | E31: Cables | F31: 1 | G31: 40 | H31: 40 | I31: Card | J31: Fatima | K31: Walk-in | L31: 10 | M31: 30 | N31: Promo discount AED 10
B32: 45723 | C32: INV-0128 | D32: Power Bank | E32: Accessories | F32: 2 | G32: 120 | H32: 240 | I32: Cash | J32: Ahmed | K32: Ali Al Falasi | L32: 15 | M32: 225 | N32: Promo discount AED 15
B33: 45723 | C33: INV-0129 | D33: Memory Card 64GB | E33: Storage | F33: 4 | G33: 45 | H33: 180 | I33: Cash | J33: Fatima | K33: Walk-in | L33: 0 | M33: 180
B34: 45724 | C34: INV-0130 | D34: Ethernet Cable | E34: Cables | F34: 4 | G34: 22 | H34: 88 | I34: Cash | J34: Ahmed | K34: Salma Al Tamimi | L34: 0 | M34: 88
B35: 45724 | C35: INV-0131 | D35: Cleaning Kit | E35: Accessories | F35: 4 | G35: 25 | H35: 100 | I35: Online | J35: Ahmed | K35: Walk-in | L35: 0 | M35: 100
B36: 45724 | C36: INV-0132 | D36: Headphones | E36: Audio | F36: 1 | G36: 200 | H36: 200 | I36: Card | J36: Omar | K36: Fatma Al Suwaidi | L36: 15 | M36: 185 | N36: Promo discount AED 15
B37: 45725 | C37: INV-0133 | D37: Adapter Plug | E37: Accessories | F37: 2 | G37: 20 | H37: 40 | I37: Card | J37: Omar | K37: Rashid Al Zaabi | L37: 10 | M37: 30 | N37: Promo discount AED 10
B38: 45725 | C38: INV-0134 | D38: Adapter Plug | E38: Accessories | F38: 1 | G38: 20 | H38: 20 | I38: Cash | J38: Khalid | K38: Mohamed Al Rashid | L38: 0 | M38: 20
B39: 45725 | C39: INV-0135 | D39: Type-C Hub | E39: Accessories | F39: 2 | G39: 95 | H39: 190 | I39: Card | J39: Sara | K39: Youssef Al Mansoori | L39: 0 | M39: 190
B40: 45725 | C40: INV-0136 | D40: Power Bank | E40: Accessories | F40: 2 | G40: 120 | H40: 240 | I40: Card | J40: Sara | K40: Saeed Al Dhaheri | L40: 0 | M40: 240
B41: 45725 | C41: INV-0137 | D41: AV Cable | E41: Cables | F41: 3 | G41: 28 | H41: 84 | I41: Card | J41: Maryam | K41: Walk-in | L41: 0 | M41: 84
B42: 45726 | C42: INV-0138 | D42: Fitness Band | E42: Wearables | F42: 2 | G42: 180 | H42: 360 | I42: Card | J42: Ahmed | K42: Walk-in | L42: 0 | M42: 360
B43: 45726 | C43: INV-0139 | D43: Power Bank | E43: Accessories | F43: 3 | G43: 120 | H43: 360 | I43: Cash | J43: Khalid | K43: Amna Al Otaiba | L43: 0 | M43: 360
B44: 45726 | C44: INV-0140 | D44: Tripod Stand | E44: Accessories | F44: 2 | G44: 90 | H44: 180 | I44: Cash | J44: Khalid | K44: Hassan Al Nuaimi | L44: 0 | M44: 180
B45: 45726 | C45: INV-0141 | D45: Earbuds | E45: Audio | F45: 1 | G45: 85 | H45: 85 | I45: Card | J45: Fatima | K45: Khalid Al Ketbi | L45: 30 | M45: 55 | N45: Promo discount AED 30
B46: 45727 | C46: INV-0142 | D46: Screen Protector | E46: Accessories | F46: 1 | G46: 30 | H46: 30 | I46: Card | J46: Khalid | K46: Walk-in | L46: 0 | M46: 30
B47: 45727 | C47: INV-0143 | D47: Wireless Charger | E47: Accessories | F47: 2 | G47: 110 | H47: 220 | I47: Card | J47: Omar | K47: Noor Al Hashmi | L47: 15 | M47: 205 | N47: Promo discount AED 15
B48: 45727 | C48: INV-0144 | D48: Portable SSD | E48: Storage | F48: 4 | G48: 250 | H48: 1000 | I48: Card | J48: Ahmed | K48: Mohamed Al Rashid | L48: 0 | M48: 1000
B49: 45728 | C49: INV-0145 | D49: Headphones | E49: Audio | F49: 1 | G49: 200 | H49: 200 | I49: Card | J49: Khalid | K49: Saeed Al Dhaheri | L49: 20 | M49: 180 | N49: Promo discount AED 20
B50: 45728 | C50: INV-0146 | D50: Earbuds | E50: Audio | F50: 2 | G50: 85 | H50: 170 | I50: Card | J50: Fatima | K50: Rashid Al Zaabi | L50: 0 | M50: 170
B51: 45728 | C51: INV-0147 | D51: Portable SSD | E51: Storage | F51: 1 | G51: 250 | H51: 250 | I51: Card | J51: Khalid | K51: Mariam Al Shamsi | L51: 0 | M51: 250
B52: 45728 | C52: INV-0148 | D52: Headphones | E52: Audio | F52: 2 | G52: 200 | H52: 400 | I52: Card | J52: Ahmed | K52: Walk-in | L52: 20 | M52: 380 | N52: Promo discount AED 20
B53: 45728 | C53: INV-0149 | D53: Charger | E53: Accessories | F53: 3 | G53: 55 | H53: 165 | I53: Cash | J53: Maryam | K53: Saeed Al Dhaheri | L53: 0 | M53: 165
B54: 45729 | C54: INV-0150 | D54: Power Bank | E54: Accessories | F54: 1 | G54: 120 | H54: 120 | I54: Card | J54: Omar | K54: Aisha Al Maktoum | L54: 50 | M54: 70 | N54: Promo discount AED 50
B55: 45729 | C55: INV-0151 | D55: Smart Watch | E55: Wearables | F55: 3 | G55: 450 | H55: 1350 | I55: Cash | J55: Sara | K55: Walk-in | L55: 0 | M55: 1350
B56: 45729 | C56: INV-0152 | D56: Phone Case | E56: Accessories | F56: 1 | G56: 45 | H56: 45 | I56: Cash | J56: Maryam | K56: Omar Khalaf | L56: 0 | M56: 45
B57: 45729 | C57: INV-0153 | D57: Stylus Pen | E57: Accessories | F57: 2 | G57: 65 | H57: 130 | I57: Card | J57: Ahmed | K57: Mariam Al Shamsi | L57: 0 | M57: 130
B58: 45730 | C58: INV-0154 | D58: Phone Holder | E58: Accessories | F58: 2 | G58: 35 | H58: 70 | I58: Card | J58: Maryam | K58: Fatma Al Suwaidi | L58: 0 | M58: 70
B59: 45730 | C59: INV-0155 | D59: Cleaning Kit | E59: Accessories | F59: 2 | G59: 25 | H59: 50 | I59: Bank Transfer | J59: Fatima | K59: Layla Al Qasimi | L59: 0 | M59: 50
B60: 45730 | C60: INV-0156 | D60: Keyboard | E60: Peripherals | F60: 4 | G60: 200 | H60: 800 | I60: Cash | J60: Maryam | K60: Ali Al Falasi | L60: 0 | M60: 800
B61: 45731 | C61: INV-0157 | D61: Type-C Hub | E61: Accessories | F61: 3 | G61: 95 | H61: 285 | I61: Cash | J61: Maryam | K61: Fatma Al Suwaidi | L61: 0 | M61: 285
B62: 45731 | C62: INV-0158 | D62: Screen Protector | E62: Accessories | F62: 4 | G62: 30 | H62: 120 | I62: Cash | J62: Sara | K62: Huda Al Ameri | L62: 0 | M62: 120
B63: 45731 | C63: INV-0159 | D63: HDMI Cable | E63: Cables | F63: 2 | G63: 35 | H63: 70 | I63: Cash | J63: Fatima | K63: Khalid Al Ketbi | L63: 0 | M63: 70
B64: 45731 | C64: INV-0160 | D64: Earbuds | E64: Audio | F64: 3 | G64: 85 | H64: 255 | I64: Card | J64: Khalid | K64: Khalid Al Ketbi | L64: 0 | M64: 255
B65: 45732 | C65: INV-0161 | D65: Monitor Cable | E65: Cables | F65: 1 | G65: 40 | H65: 40 | I65: Cash | J65: Omar | K65: Layla Al Qasimi | L65: 0 | M65: 40
B66: 45732 | C66: INV-0162 | D66: Wireless Charger | E66: Accessories | F66: 1 | G66: 110 | H66: 110 | I66: Cash | J66: Sara | K66: Huda Al Ameri | L66: 0 | M66: 110
... B71: 45733 | C71: INV-0167 | D71: USB Flash Drive | E71: Storage | F71: 2 | G71: 30 | H71: 60 | I71: Cash | J71: Maryam | K71: Khalid Al Ketbi | L71: 0 | M71: 60
B72: 45733 | C72: INV-0168 | D72: Keyboard | E72: Peripherals | F72: 3 | G72: 200 | H72: 600 | I72: Card | J72: Ahmed | K72: Mariam Al Shamsi | L72: 25 | M72: 575 | N72: Promo discount AED 25
B73: 45733 | C73: INV-0169 | D73: Webcam | E73: Peripherals | F73: 4 | G73: 180 | H73: 720 | I73: Card | J73: Maryam | K73: Youssef Al Mansoori | L73: 0 | M73: 720
B74: 45733 | C74: INV-0170 | D74: Laptop Stand | E74: Accessories | F74: 1 | G74: 150 | H74: 150 | I74: Card | J74: Maryam | K74: Walk-in | L74: 0 | M74: 150
B75: 45734 | C75: INV-0171 | D75: Type-C Hub | E75: Accessories | F75: 3 | G75: 95 | H75: 285 | I75: Cash | J75: Fatima | K75: Omar Khalaf | L75: 15 | M75: 270 | N75: Promo discount AED 15
B76: 45734 | C76: INV-0172 | D76: Ethernet Cable | E76: Cables | F76: 1 | G76: 22 | H76: 22 | I76: Card | J76: Maryam | K76: Walk-in | L76: 40 | M76: -18 | N76: Promo discount AED 40
B77: 45734 | C77: INV-0173 | D77: Car Mount | E77: Accessories | F77: 4 | G77: 50 | H77: 200 | I77: Card | J77: Fatima | K77: Walk-in | L77: 0 | M77: 200
B78: 45735 | C78: INV-0174 | D78: Mouse Pad XL | E78: Peripherals | F78: 2 | G78: 40 | H78: 80 | I78: Cash | J78: Maryam | K78: Walk-in | L78: 0 | M78: 80
B79: 45735 | C79: INV-0175 | D79: Type-C Hub | E79: Accessories | F79: 1 | G79: 95 | H79: 95 | I79: Card | J79: Sara | K79: Walk-in | L79: 0 | M79: 95
B80: 45735 | C80: INV-0176 | D80: Webcam | E80: Peripherals | F80: 4 | G80: 180 | H80: 720 | I80: Card | J80: Maryam | K80: Walk-in | L80: 0 | M80: 720
B81: 45736 | C81: INV-0177 | D81: Adapter Plug | E81: Accessories | F81: 2 | G81: 20 | H81: 40 | I81: Online | J81: Sara | K81: Rashid Al Zaabi | L81: 15 | M81: 25 | N81: Promo discount AED 15
B82: 45736 | C82: INV-0178 | D82: Memory Card 64GB | E82: Storage | F82: 4 | G82: 45 | H82: 180 | I82: Card | J82: Omar | K82: Rashid Al Zaabi | L82: 20 | M82: 160 | N82: Promo discount AED 20
B83: 45736 | C83: INV-0179 | D83: Type-C Hub | E83: Accessories | F83: 3 | G83: 95 | H83: 285 | I83: Card | J83: Khalid | K83: Hassan Al Nuaimi | L83: 15 | M83: 270 | N83: Promo discount AED 15
B84: 45736 | C84: INV-0180 | D84: Car Mount | E84: Accessories | F84: 2 | G84: 50 | H84: 100 | I84: Online | J84: Ahmed | K84: Salma Al Tamimi | L84: 0 | M84: 100
B85: 45736 | C85: INV-0181 | D85: AV Cable | E85: Cables | F85: 4 | G85: 28 | H85: 112 | I85: Cash | J85: Sara | K85: Khalid Al Ketbi | L85: 0 | M85: 112
B86: 45737 | C86: INV-0182 | D86: USB Cable | E86: Accessories | F86: 4 | G86: 25 | H86: 100 | I86: Card | J86: Omar | K86: Mariam Al Shamsi | L86: 0 | M86: 100
B87: 45737 | C87: INV-0183 | D87: Cleaning Kit | E87: Accessories | F87: 2 | G87: 25 | H87: 50 | I87: Card | J87: Omar | K87: Salma Al Tamimi | L87: 0 | M87: 50
B88: 45737 | C88: INV-0184 | D88: Car Mount | E88: Accessories | F88: 3 | G88: 50 | H88: 150 | I88: Card | J88: Sara | K88: Layla Al Qasimi | L88: 0 | M88: 150
B89: 45737 | C89: INV-0185 | D89: Smart Watch | E89: Wearables | F89: 1 | G89: 450 | H89: 450 | I89: Bank Transfer | J89: Khalid | K89: Walk-in | L89: 0 | M89: 450
B90: 45737 | C90: INV-0186 | D90: Bluetooth Speaker | E90: Audio | F90: 4 | G90: 150 | H90: 600 | I90: Cash | J90: Sara | K90: Layla Al Qasimi | L90: 25 | M90: 575 | N90: Promo discount AED 25
B91: 45738 | C91: INV-0187 | D91: Charger | E91: Accessories | F91: 4 | G91: 55 | H91: 220 | I91: Card | J91: Sara | K91: Saeed Al Dhaheri | L91: 0 | M91: 220
B92: 45738 | C92: INV-0188 | D92: Cleaning Kit | E92: Accessories | F92: 3 | G92: 25 | H92: 75 | I92: Online | J92: Sara | K92: Mohamed Al Rashid | L92: 0 | M92: 75
B93: 45738 | C93: INV-0189 | D93: Power Bank | E93: Accessories | F93: 3 | G93: 120 | H93: 360 | I93: Cash | J93: Ahmed | K93: Walk-in | L93: 10 | M93: 350 | N93: Promo discount AED 10
B94: 45738 | C94: INV-0190 | D94: Type-C Hub | E94: Accessories | F94: 2 | G94: 95 | H94: 190 | I94: Online | J94: Khalid | K94: Omar Khalaf | L94: 25 | M94: 165 | N94: Promo discount AED 25
B95: 45739 | C95: INV-0191 | D95: Tablet | E95: Devices | F95: 2 | G95: 899 | H95: 1798 | I95: Card | J95: Omar | K95: Huda Al Ameri | L95: 30 | M95: 1768 | N95: Promo discount AED 30
B96: 45739 | C96: INV-0192 | D96: Tablet | E96: Devices | F96: 2 | G96: 899 | H96: 1798 | I96: Bank Transfer | J96: Ahmed | K96: Walk-in | L96: 20 | M96: 1778 | N96: Promo discount AED 20
B97: 45739 | C97: INV-0193 | D97: Car Mount | E97: Accessories | F97: 4 | G97: 50 | H97: 200 | I97: Bank Transfer | J97: Fatima | K97: Hassan Al Nuaimi | L97: 0 | M97: 200
B98: 45739 | C98: INV-0194 | D98: Type-C Hub | E98: Accessories | F98: 1 | G98: 95 | H98: 95 | I98: Card | J98: Omar | K98: Walk-in | L98: 0 | M98: 95
B99: 45739 | C99: INV-0195 | D99: Screen Protector | E99: Accessories | F99: 3 | G99: 30 | H99: 90 | I99: Card | J99: Maryam | K99: Huda Al Ameri | L99: 40 | M99: 50 | N99: Promo discount AED 40
B100: 45740 | C100: INV-0196 | D100: Phone Case | E100: Accessories | F100: 4 | G100: 45 | H100: 180 | I100: Online | J100: Ahmed | K100: Salma Al Tamimi | L100: 0 | M100: 180
B101: 45740 | C101: INV-0197 | D101: AV Cable | E101: Cables | F101: 2 | G101: 28 | H101: 56 | I101: Card | J101: Maryam | K101: Walk-in | L101: 0 | M101: 56
B102: 45740 | C102: INV-0198 | D102: Memory Card 64GB | E102: Storage | F102: 4 | G102: 45 | H102: 180 | I102: Card | J102: Maryam | K102: Walk-in | L102: 50 | M102: 130 | N102: Promo discount AED 50
B103: 45740 | C103: INV-0199 | D103: Type-C Hub | E103: Accessories | F103: 1 | G103: 95 | H103: 95 | I103: Card | J103: Sara | K103: Noor Al Hashmi | L103: 0 | M103: 95
B104: 45741 | C104: INV-0200 | D104: Car Mount | E104: Accessories | F104: 3 | G104: 50 | H104: 150 | I104: Cash | J104: Omar | K104: Layla Al Qasimi | L104: 0 | M104: 150
B105: 45741 | C105: INV-0201 | D105: Phone Holder | E105: Accessories | F105: 3 | G105: 35 | H105: 105 | I105: Card | J105: Khalid | K105: Saeed Al Dhaheri | L105: 0 | M105: 105
B106: 45741 | C106: INV-0202 | D106: Tripod Stand | E106: Accessories | F106: 2 | G106: 90 | H106: 180 | I106: Cash | J106: Maryam | K106: Salma Al Tamimi | L106: 0 | M106: 180
...

Sheet Daily Summary
B2: Daily Summary — March 2025
B4: Date | C4: Total Sales | D4: # Transactions | E4: Avg Transaction | F4: Cash | G4: Card | H4: Online | I4: Bank Transfer | J4: # Items Sold | K4: Total Discount Given
B5: 45717 | C5: =SUMPRODUCT(('Sales Entry'!B5:B131=B5)*('Sales Entry'!M5:M131)) | D5: =SUMPRODUCT(('Sales Entry'!B5:B131=B5)*1) | E5: =IFERROR(C5/D5,0) | F5: =SUMPRODUCT(('Sales Entry'!B5:B131=B5)*('Sales Entry'!I5:I131="Cash")*('Sales Entry'!M5:M131)) | G5: =SUMPRODUCT(('Sales Entry'!B5:B131=B5)*('Sales Entry'!I5:I131="Card")*('Sales Entry'!M5:M131)) | H5: =SUMPRODUCT(('Sales Entry'!B5:B131=B5)*('Sales Entry'!I5:I131="Online")*('Sales Entry'!M5:M131)) | I5: =SUMPRODUCT(('Sales Entry'!B5:B131=B5)*('Sales Entry'!I5:I131="Bank Transfer")*('Sales Entry'!M5:M131)) | J5: =SUMPRODUCT(('Sales Entry'!B5:B131=B5)*('Sales Entry'!F5:F131)) | K5: =SUMPRODUCT(('Sales Entry'!B5:B131=B5)*('Sales Entry'!L5:L131))
B6: 45718 | C6: =SUMPRODUCT(('Sales Entry'!B5:B131=B6)*('Sales Entry'!M5:M131)) | D6: =SUMPRODUCT(('Sales Entry'!B5:B131=B6)*1) | E6: =IFERROR(C6/D6,0) | F6: =SUMPRODUCT(('Sales Entry'!B5:B131=B6)*('Sales Entry'!I5:I131="Cash")*('Sales Entry'!M5:M131)) | G6: =SUMPRODUCT(('Sales Entry'!B5:B131=B6)*('Sales Entry'!I5:I131="Card")*('Sales Entry'!M5:M131)) | H6: =SUMPRODUCT(('Sales Entry'!B5:B131=B6)*('Sales Entry'!I5:I131="Online")*('Sales Entry'!M5:M131)) | I6: =SUMPRODUCT(('Sales Entry'!B5:B131=B6)*('Sales Entry'!I5:I131="Bank Transfer")*('Sales Entry'!M5:M131)) | J6: =SUMPRODUCT(('Sales Entry'!B5:B131=B6)*('Sales Entry'!F5:F131)) | K6: =SUMPRODUCT(('Sales Entry'!B5:B131=B6)*('Sales Entry'!L5:L131))
B7: 45719 | C7: =SUMPRODUCT(('Sales Entry'!B5:B131=B7)*('Sales Entry'!M5:M131)) | D7: =SUMPRODUCT(('Sales Entry'!B5:B131=B7)*1) | E7: =IFERROR(C7/D7,0) | F7: =SUMPRODUCT(('Sales Entry'!B5:B131=B7)*('Sales Entry'!I5:I131="Cash")*('Sales Entry'!M5:M131)) | G7: =SUMPRODUCT(('Sales Entry'!B5:B131=B7)*('Sales Entry'!I5:I131="Card")*('Sales Entry'!M5:M131)) | H7: =SUMPRODUCT(('Sales Entry'!B5:B131=B7)*('Sales Entry'!I5:I131="Online")*('Sales Entry'!M5:M131)) | I7: =SUMPRODUCT(('Sales Entry'!B5:B131=B7)*('Sales Entry'!I5:I131="Bank Transfer")*('Sales Entry'!M5:M131)) | J7: =SUMPRODUCT(('Sales Entry'!B5:B131=B7)*('Sales Entry'!F5:F131)) | K7: =SUMPRODUCT(('Sales Entry'!B5:B131=B7)*('Sales Entry'!L5:L131))
B8: 45720 | C8: =SUMPRODUCT(('Sales Entry'!B5:B131=B8)*('Sales Entry'!M5:M131)) | D8: =SUMPRODUCT(('Sales Entry'!B5:B131=B8)*1) | E8: =IFERROR(C8/D8,0) | F8: =SUMPRODUCT(('Sales Entry'!B5:B131=B8)*('Sales Entry'!I5:I131="Cash")*('Sales Entry'!M5:M131)) | G8: =SUMPRODUCT(('Sales Entry'!B5:B131=B8)*('Sales Entry'!I5:I131="Card")*('Sales Entry'!M5:M131)) | H8: =SUMPRODUCT(('Sales Entry'!B5:B131=B8)*('Sales Entry'!I5:I131="Online")*('Sales Entry'!M5:M131)) | I8: =SUMPRODUCT(('Sales Entry'!B5:B131=B8)*('Sales Entry'!I5:I131="Bank Transfer")*('Sales Entry'!M5:M131)) | J8: =SUMPRODUCT(('Sales Entry'!B5:B131=B8)*('Sales Entry'!F5:F131)) | K8: =SUMPRODUCT(('Sales Entry'!B5:B131=B8)*('Sales Entry'!L5:L131))
B9: 45721 | C9: =SUMPRODUCT(('Sales Entry'!B5:B131=B9)*('Sales Entry'!M5:M131)) | D9: =SUMPRODUCT(('Sales Entry'!B5:B131=B9)*1) | E9: =IFERROR(C9/D9,0) | F9: =SUMPRODUCT(('Sales Entry'!B5:B131=B9)*('Sales Entry'!I5:I131="Cash")*('Sales Entry'!M5:M131)) | G9: =SUMPRODUCT(('Sales Entry'!B5:B131=B9)*('Sales Entry'!I5:I131="Card")*('Sales Entry'!M5:M131)) | H9: =SUMPRODUCT(('Sales Entry'!B5:B131=B9)*('Sales Entry'!I5:I131="Online")*('Sales Entry'!M5:M131)) | I9: =SUMPRODUCT(('Sales Entry'!B5:B131=B9)*('Sales Entry'!I5:I131="Bank Transfer")*('Sales Entry'!M5:M131)) | J9: =SUMPRODUCT(('Sales Entry'!B5:B131=B9)*('Sales Entry'!F5:F131)) | K9: =SUMPRODUCT(('Sales Entry'!B5:B131=B9)*('Sales Entry'!L5:L131))
B10: 45722 | C10: =SUMPRODUCT(('Sales Entry'!B5:B131=B10)*('Sales Entry'!M5:M131)) | D10: =SUMPRODUCT(('Sales Entry'!B5:B131=B10)*1) | E10: =IFERROR(C10/D10,0) | F10: =SUMPRODUCT(('Sales Entry'!B5:B131=B10)*('Sales Entry'!I5:I131="Cash")*('Sales Entry'!M5:M131)) | G10: =SUMPRODUCT(('Sales Entry'!B5:B131=B10)*('Sales Entry'!I5:I131="Card")*('Sales Entry'!M5:M131)) | H10: =SUMPRODUCT(('Sales Entry'!B5:B131=B10)*('Sales Entry'!I5:I131="Online")*('Sales Entry'!M5:M131)) | I10: =SUMPRODUCT(('Sales Entry'!B5:B131=B10)*('Sales Entry'!I5:I131="Bank Transfer")*('Sales Entry'!M5:M131)) | J10: =SUMPRODUCT(('Sales Entry'!B5:B131=B10)*('Sales Entry'!F5:F131)) | K10: =SUMPRODUCT(('Sales Entry'!B5:B131=B10)*('Sales Entry'!L5:L131))
B11: 45723 | C11: =SUMPRODUCT(('Sales Entry'!B5:B131=B11)*('Sales Entry'!M5:M131)) | D11: =SUMPRODUCT(('Sales Entry'!B5:B131=B11)*1) | E11: =IFERROR(C11/D11,0) | F11: =SUMPRODUCT(('Sales Entry'!B5:B131=B11)*('Sales Entry'!I5:I131="Cash")*('Sales Entry'!M5:M131)) | G11: =SUMPRODUCT(('Sales Entry'!B5:B131=B11)*('Sales Entry'!I5:I131="Card")*('Sales Entry'!M5:M131)) | H11: =SUMPRODUCT(('Sales Entry'!B5:B131=B11)*('Sales Entry'!I5:I131="Online")*('Sales Entry'!M5:M131)) | I11: =SUMPRODUCT(('Sales Entry'!B5:B131=B11)*('Sales Entry'!I5:I131="Bank Transfer")*('Sales Entry'!M5:M131)) | J11: =SUMPRODUCT(('Sales Entry'!B5:B131=B11)*('Sales Entry'!F5:F131)) | K11: =SUMPRODUCT(('Sales Entry'!B5:B131=B11)*('Sales Entry'!L5:L131))
B12: 45724 | C12: =SUMPRODUCT(('Sales Entry'!B5:B131=B12)*('Sales Entry'!M5:M131)) | D12: =SUMPRODUCT(('Sales Entry'!B5:B131=B12)*1) | E12: =IFERROR(C12/D12,0) | F12: =SUMPRODUCT(('Sales Entry'!B5:B131=B12)*('Sales Entry'!I5:I131="Cash")*('Sales Entry'!M5:M131)) | G12: =SUMPRODUCT(('Sales Entry'!B5:B131=B12)*('Sales Entry'!I5:I131="Card")*('Sales Entry'!M5:M131)) | H12: =SUMPRODUCT(('Sales Entry'!B5:B131=B12)*('Sales Entry'!I5:I131="Online")*('Sales Entry'!M5:M131)) | I12: =SUMPRODUCT(('Sales Entry'!B5:B131=B12)*('Sales Entry'!I5:I131="Bank Transfer")*('Sales Entry'!M5:M131)) | J12: =SUMPRODUCT(('Sales Entry'!B5:B131=B12)*('Sales Entry'!F5:F131)) | K12: =SUMPRODUCT(('Sales Entry'!B5:B131=B12)*('Sales Entry'!L5:L131))
B13: 45725 | C13: =SUMPRODUCT(('Sales Entry'!B5:B131=B13)*('Sales Entry'!M5:M131)) | D13: =SUMPRODUCT(('Sales Entry'!B5:B131=B13)*1) | E13: =IFERROR(C13/D13,0) | F13: =SUMPRODUCT(('Sales Entry'!B5:B131=B13)*('Sales Entry'!I5:I131="Cash")*('Sales Entry'!M5:M131)) | G13: =SUMPRODUCT(('Sales Entry'!B5:B131=B13)*('Sales Entry'!I5:I131="Card")*('Sales Entry'!M5:M131)) | H13: =SUMPRODUCT(('Sales Entry'!B5:B131=B13)*('Sales Entry'!I5:I131="Online")*('Sales Entry'!M5:M131)) | I13: =SUMPRODUCT(('Sales Entry'!B5:B131=B13)*('Sales Entry'!I5:I131="Bank Transfer")*('Sales Entry'!M5:M131)) | J13: =SUMPRODUCT(('Sales Entry'!B5:B131=B13)*('Sales Entry'!F5:F131)) | K13: =SUMPRODUCT(('Sales Entry'!B5:B131=B13)*('Sales Entry'!L5:L131))
B14: 45726 | C14: =SUMPRODUCT(('Sales Entry'!B5:B131=B14)*('Sales Entry'!M5:M131)) | D14: =SUMPRODUCT(('Sales Entry'!B5:B131=B14)*1) | E14: =IFERROR(C14/D14,0) | F14: =SUMPRODUCT(('Sales Entry'!B5:B131=B14)*('Sales Entry'!I5:I131="Cash")*('Sales Entry'!M5:M131)) | G14: =SUMPRODUCT(('Sales Entry'!B5:B131=B14)*('Sales Entry'!I5:I131="Card")*('Sales Entry'!M5:M131)) | H14: =SUMPRODUCT(('Sales Entry'!B5:B131=B14)*('Sales Entry'!I5:I131="Online")*('Sales Entry'!M5:M131)) | I14: =SUMPRODUCT(('Sales Entry'!B5:B131=B14)*('Sales Entry'!I5:I131="Bank Transfer")*('Sales Entry'!M5:M131)) | J14: =SUMPRODUCT(('Sales Entry'!B5:B131=B14)*('Sales Entry'!F5:F131)) | K14: =SUMPRODUCT(('Sales Entry'!B5:B131=B14)*('Sales Entry'!L5:L131))
B15: 45727 | C15: =SUMPRODUCT(('Sales Entry'!B5:B131=B15)*('Sales Entry'!M5:M131)) | D15: =SUMPRODUCT(('Sales Entry'!B5:B131=B15)*1) | E15: =IFERROR(C15/D15,0) | F15: =SUMPRODUCT(('Sales Entry'!B5:B131=B15)*('Sales Entry'!I5:I131="Cash")*('Sales Entry'!M5:M131)) | G15: =SUMPRODUCT(('Sales Entry'!B5:B131=B15)*('Sales Entry'!I5:I131="Card")*('Sales Entry'!M5:M131)) | H15: =SUMPRODUCT(('Sales Entry'!B5:B131=B15)*('Sales Entry'!I5:I131="Online")*('Sales Entry'!M5:M131)) | I15: =SUMPRODUCT(('Sales Entry'!B5:B131=B15)*('Sales Entry'!I5:I131="Bank Transfer")*('Sales Entry'!M5:M131)) | J15: =SUMPRODUCT(('Sales Entry'!B5:B131=B15)*('Sales Entry'!F5:F131)) | K15: =SUMPRODUCT(('Sales Entry'!B5:B131=B15)*('Sales Entry'!L5:L131))
B16: 45728 | C16: =SUMPRODUCT(('Sales Entry'!B5:B131=B16)*('Sales Entry'!M5:M131)) | D16: =SUMPRODUCT(('Sales Entry'!B5:B131=B16)*1) | E16: =IFERROR(C16/D16,0) | F16: =SUMPRODUCT(('Sales Entry'!B5:B131=B16)*('Sales Entry'!I5:I131="Cash")*('Sales Entry'!M5:M131)) | G16: =SUMPRODUCT(('Sales Entry'!B5:B131=B16)*('Sales Entry'!I5:I131="Card")*('Sales Entry'!M5:M131)) | H16: =SUMPRODUCT(('Sales Entry'!B5:B131=B16)*('Sales Entry'!I5:I131="Online")*('Sales Entry'!M5:M131)) | I16: =SUMPRODUCT(('Sales Entry'!B5:B131=B16)*('Sales Entry'!I5:I131="Bank Transfer")*('Sales Entry'!M5:M131)) | J16: =SUMPRODUCT(('Sales Entry'!B5:B131=B16)*('Sales Entry'!F5:F131)) | K16: =SUMPRODUCT(('Sales Entry'!B5:B131=B16)*('Sales Entry'!L5:L131))
B17: 45729 | C17: =SUMPRODUCT(('Sales Entry'!B5:B131=B17)*('Sales Entry'!M5:M131)) | D17: =SUMPRODUCT(('Sales Entry'!B5:B131=B17)*1) | E17: =IFERROR(C17/D17,0) | F17: =SUMPRODUCT(('Sales Entry'!B5:B131=B17)*('Sales Entry'!I5:I131="Cash")*('Sales Entry'!M5:M131)) | G17: =SUMPRODUCT(('Sales Entry'!B5:B131=B17)*('Sales Entry'!I5:I131="Card")*('Sales Entry'!M5:M131)) | H17: =SUMPRODUCT(('Sales Entry'!B5:B131=B17)*('Sales Entry'!I5:I131="Online")*('Sales Entry'!M5:M131)) | I17: =SUMPRODUCT(('Sales Entry'!B5:B131=B17)*('Sales Entry'!I5:I131="Bank Transfer")*('Sales Entry'!M5:M131)) | J17: =SUMPRODUCT(('Sales Entry'!B5:B131=B17)*('Sales Entry'!F5:F131)) | K17: =SUMPRODUCT(('Sales Entry'!B5:B131=B17)*('Sales Entry'!L5:L131))
B18: 45730 | C18: =SUMPRODUCT(('Sales Entry'!B5:B131=B18)*('Sales Entry'!M5:M131)) | D18: =SUMPRODUCT(('Sales Entry'!B5:B131=B18)*1) | E18: =IFERROR(C18/D18,0) | F18: =SUMPRODUCT(('Sales Entry'!B5:B131=B18)*('Sales Entry'!I5:I131="Cash")*('Sales Entry'!M5:M131)) | G18: =SUMPRODUCT(('Sales Entry'!B5:B131=B18)*('Sales Entry'!I5:I131="Card")*('Sales Entry'!M5:M131)) | H18: =SUMPRODUCT(('Sales Entry'!B5:B131=B18)*('Sales Entry'!I5:I131="Online")*('Sales Entry'!M5:M131)) | I18: =SUMPRODUCT(('Sales Entry'!B5:B131=B18)*('Sales Entry'!I5:I131="Bank Transfer")*('Sales Entry'!M5:M131)) | J18: =SUMPRODUCT(('Sales Entry'!B5:B131=B18)*('Sales Entry'!F5:F131)) | K18: =SUMPRODUCT(('Sales Entry'!B5:B131=B18)*('Sales Entry'!L5:L131))
B19: 45731 | C19: =SUMPRODUCT(('Sales Entry'!B5:B131=B19)*('Sales Entry'!M5:M131)) | D19: =SUMPRODUCT(('Sales Entry'!B5:B131=B19)*1) | E19: =IFERROR(C19/D19,0) | F19: =SUMPRODUCT(('Sales Entry'!B5:B131=B19)*('Sales Entry'!I5:I131="Cash")*('Sales Entry'!M5:M131)) | G19: =SUMPRODUCT(('Sales Entry'!B5:B131=B19)*('Sales Entry'!I5:I131="Card")*('Sales Entry'!M5:M131)) | H19: =SUMPRODUCT(('Sales Entry'!B5:B131=B19)*('Sales Entry'!I5:I131="Online")*('Sales Entry'!M5:M131)) | I19: =SUMPRODUCT(('Sales Entry'!B5:B131=B19)*('Sales Entry'!I5:I131="Bank Transfer")*('Sales Entry'!M5:M131)) | J19: =SUMPRODUCT(('Sales Entry'!B5:B131=B19)*('Sales Entry'!F5:F131)) | K19: =SUMPRODUCT(('Sales Entry'!B5:B131=B19)*('Sales Entry'!L5:L131))
B20: 45732 | C20: =SUMPRODUCT(('Sales Entry'!B5:B131=B20)*('Sales Entry'!M5:M131)) | D20: =SUMPRODUCT(('Sales Entry'!B5:B131=B20)*1) | E20: =IFERROR(C20/D20,0) | F20: =SUMPRODUCT(('Sales Entry'!B5:B131=B20)*('Sales Entry'!I5:I131="Cash")*('Sales Entry'!M5:M131)) | G20: =SUMPRODUCT(('Sales Entry'!B5:B131=B20)*('Sales Entry'!I5:I131="Card")*('Sales Entry'!M5:M131)) | H20: =SUMPRODUCT(('Sales Entry'!B5:B131=B20)*('Sales Entry'!I5:I131="Online")*('Sales Entry'!M5:M131)) | I20: =SUMPRODUCT(('Sales Entry'!B5:B131=B20)*('Sales Entry'!I5:I131="Bank Transfer")*('Sales Entry'!M5:M131)) | J20: =SUMPRODUCT(('Sales Entry'!B5:B131=B20)*('Sales Entry'!F5:F131)) | K20: =SUMPRODUCT(('Sales Entry'!B5:B131=B20)*('Sales Entry'!L5:L131))
B21: 45733 | C21: =SUMPRODUCT(('Sales Entry'!B5:B131=B21)*('Sales Entry'!M5:M131)) | D21: =SUMPRODUCT(('Sales Entry'!B5:B131=B21)*1) | E21: =IFERROR(C21/D21,0) | F21: =SUMPRODUCT(('Sales Entry'!B5:B131=B21)*('Sales Entry'!I5:I131="Cash")*('Sales Entry'!M5:M131)) | G21: =SUMPRODUCT(('Sales Entry'!B5:B131=B21)*('Sales Entry'!I5:I131="Card")*('Sales Entry'!M5:M131)) | H21: =SUMPRODUCT(('Sales Entry'!B5:B131=B21)*('Sales Entry'!I5:I131="Online")*('Sales Entry'!M5:M131)) | I21: =SUMPRODUCT(('Sales Entry'!B5:B131=B21)*('Sales Entry'!I5:I131="Bank Transfer")*('Sales Entry'!M5:M131)) | J21: =SUMPRODUCT(('Sales Entry'!B5:B131=B21)*('Sales Entry'!F5:F131)) | K21: =SUMPRODUCT(('Sales Entry'!B5:B131=B21)*('Sales Entry'!L5:L131))
B22: 45734 | C22: =SUMPRODUCT(('Sales Entry'!B5:B131=B22)*('Sales Entry'!M5:M131)) | D22: =SUMPRODUCT(('Sales Entry'!B5:B131=B22)*1) | E22: =IFERROR(C22/D22,0) | F22: =SUMPRODUCT(('Sales Entry'!B5:B131=B22)*('Sales Entry'!I5:I131="Cash")*('Sales Entry'!M5:M131)) | G22: =SUMPRODUCT(('Sales Entry'!B5:B131=B22)*('Sales Entry'!I5:I131="Card")*('Sales Entry'!M5:M131)) | H22: =SUMPRODUCT(('Sales Entry'!B5:B131=B22)*('Sales Entry'!I5:I131="Online")*('Sales Entry'!M5:M131)) | I22: =SUMPRODUCT(('Sales Entry'!B5:B131=B22)*('Sales Entry'!I5:I131="Bank Transfer")*('Sales Entry'!M5:M131)) | J22: =SUMPRODUCT(('Sales Entry'!B5:B131=B22)*('Sales Entry'!F5:F131)) | K22: =SUMPRODUCT(('Sales Entry'!B5:B131=B22)*('Sales Entry'!L5:L131))
B23: 45735 | C23: =SUMPRODUCT(('Sales Entry'!B5:B131=B23)*('Sales Entry'!M5:M131)) | D23: =SUMPRODUCT(('Sales Entry'!B5:B131=B23)*1) | E23: =IFERROR(C23/D23,0) | F23: =SUMPRODUCT(('Sales Entry'!B5:B131=B23)*('Sales Entry'!I5:I131="Cash")*('Sales Entry'!M5:M131)) | G23: =SUMPRODUCT(('Sales Entry'!B5:B131=B23)*('Sales Entry'!I5:I131="Card")*('Sales Entry'!M5:M131)) | H23: =SUMPRODUCT(('Sales Entry'!B5:B131=B23)*('Sales Entry'!I5:I131="Online")*('Sales Entry'!M5:M131)) | I23: =SUMPRODUCT(('Sales Entry'!B5:B131=B23)*('Sales Entry'!I5:I131="Bank Transfer")*('Sales Entry'!M5:M131)) | J23: =SUMPRODUCT(('Sales Entry'!B5:B131=B23)*('Sales Entry'!F5:F131)) | K23: =SUMPRODUCT(('Sales Entry'!B5:B131=B23)*('Sales Entry'!L5:L131))
B24: 45736 | C24: =SUMPRODUCT(('Sales Entry'!B5:B131=B24)*('Sales Entry'!M5:M131)) | D24: =SUMPRODUCT(('Sales Entry'!B5:B131=B24)*1) | E24: =IFERROR(C24/D24,0) | F24: =SUMPRODUCT(('Sales Entry'!B5:B131=B24)*('Sales Entry'!I5:I131="Cash")*('Sales Entry'!M5:M131)) | G24: =SUMPRODUCT(('Sales Entry'!B5:B131=B24)*('Sales Entry'!I5:I131="Card")*('Sales Entry'!M5:M131)) | H24: =SUMPRODUCT(('Sales Entry'!B5:B131=B24)*('Sales Entry'!I5:I131="Online")*('Sales Entry'!M5:M131)) | I24: =SUMPRODUCT(('Sales Entry'!B5:B131=B24)*('Sales Entry'!I5:I131="Bank Transfer")*('Sales Entry'!M5:M131)) | J24: =SUMPRODUCT(('Sales Entry'!B5:B131=B24)*('Sales Entry'!F5:F131)) | K24: =SUMPRODUCT(('Sales Entry'!B5:B131=B24)*('Sales Entry'!L5:L131))
B25: 45737 | C25: =SUMPRODUCT(('Sales Entry'!B5:B131=B25)*('Sales Entry'!M5:M131)) | D25: =SUMPRODUCT(('Sales Entry'!B5:B131=B25)*1) | E25: =IFERROR(C25/D25,0) | F25: =SUMPRODUCT(('Sales Entry'!B5:B131=B25)*('Sales Entry'!I5:I131="Cash")*('Sales Entry'!M5:M131)) | G25: =SUMPRODUCT(('Sales Entry'!B5:B131=B25)*('Sales Entry'!I5:I131="Card")*('Sales Entry'!M5:M131)) | H25: =SUMPRODUCT(('Sales Entry'!B5:B131=B25)*('Sales Entry'!I5:I131="Online")*('Sales Entry'!M5:M131)) | I25: =SUMPRODUCT(('Sales Entry'!B5:B131=B25)*('Sales Entry'!I5:I131="Bank Transfer")*('Sales Entry'!M5:M131)) | J25: =SUMPRODUCT(('Sales Entry'!B5:B131=B25)*('Sales Entry'!F5:F131)) | K25: =SUMPRODUCT(('Sales Entry'!B5:B131=B25)*('Sales Entry'!L5:L131))
B26: 45738 | C26: =SUMPRODUCT(('Sales Entry'!B5:B131=B26)*('Sales Entry'!M5:M131)) | D26: =SUMPRODUCT(('Sales Entry'!B5:B131=B26)*1) | E26: =IFERROR(C26/D26,0) | F26: =SUMPRODUCT(('Sales Entry'!B5:B131=B26)*('Sales Entry'!I5:I131="Cash")*('Sales Entry'!M5:M131)) | G26: =SUMPRODUCT(('Sales Entry'!B5:B131=B26)*('Sales Entry'!I5:I131="Card")*('Sales Entry'!M5:M131)) | H26: =SUMPRODUCT(('Sales Entry'!B5:B131=B26)*('Sales Entry'!I5:I131="Online")*('Sales Entry'!M5:M131)) | I26: =SUMPRODUCT(('Sales Entry'!B5:B131=B26)*('Sales Entry'!I5:I131="Bank Transfer")*('Sales Entry'!M5:M131)) | J26: =SUMPRODUCT(('Sales Entry'!B5:B131=B26)*('Sales Entry'!F5:F131)) | K26: =SUMPRODUCT(('Sales Entry'!B5:B131=B26)*('Sales Entry'!L5:L131))
B27: 45739 | C27: =SUMPRODUCT(('Sales Entry'!B5:B131=B27)*('Sales Entry'!M5:M131)) | D27: =SUMPRODUCT(('Sales Entry'!B5:B131=B27)*1) | E27: =IFERROR(C27/D27,0) | F27: =SUMPRODUCT(('Sales Entry'!B5:B131=B27)*('Sales Entry'!I5:I131="Cash")*('Sales Entry'!M5:M131)) | G27: =SUMPRODUCT(('Sales Entry'!B5:B131=B27)*('Sales Entry'!I5:I131="Card")*('Sales Entry'!M5:M131)) | H27: =SUMPRODUCT(('Sales Entry'!B5:B131=B27)*('Sales Entry'!I5:I131="Online")*('Sales Entry'!M5:M131)) | I27: =SUMPRODUCT(('Sales Entry'!B5:B131=B27)*('Sales Entry'!I5:I131="Bank Transfer")*('Sales Entry'!M5:M131)) | J27: =SUMPRODUCT(('Sales Entry'!B5:B131=B27)*('Sales Entry'!F5:F131)) | K27: =SUMPRODUCT(('Sales Entry'!B5:B131=B27)*('Sales Entry'!L5:L131))
B28: 45740 | C28: =SUMPRODUCT(('Sales Entry'!B5:B131=B28)*('Sales Entry'!M5:M131)) | D28: =SUMPRODUCT(('Sales Entry'!B5:B131=B28)*1) | E28: =IFERROR(C28/D28,0) | F28: =SUMPRODUCT(('Sales Entry'!B5:B131=B28)*('Sales Entry'!I5:I131="Cash")*('Sales Entry'!M5:M131)) | G28: =SUMPRODUCT(('Sales Entry'!B5:B131=B28)*('Sales Entry'!I5:I131="Card")*('Sales Entry'!M5:M131)) | H28: =SUMPRODUCT(('Sales Entry'!B5:B131=B28)*('Sales Entry'!I5:I131="Online")*('Sales Entry'!M5:M131)) | I28: =SUMPRODUCT(('Sales Entry'!B5:B131=B28)*('Sales Entry'!I5:I131="Bank Transfer")*('Sales Entry'!M5:M131)) | J28: =SUMPRODUCT(('Sales Entry'!B5:B131=B28)*('Sales Entry'!F5:F131)) | K28: =SUMPRODUCT(('Sales Entry'!B5:B131=B28)*('Sales Entry'!L5:L131))
B29: 45741 | C29: =SUMPRODUCT(('Sales Entry'!B5:B131=B29)*('Sales Entry'!M5:M131)) | D29: =SUMPRODUCT(('Sales Entry'!B5:B131=B29)*1) | E29: =IFERROR(C29/D29,0) | F29: =SUMPRODUCT(('Sales Entry'!B5:B131=B29)*('Sales Entry'!I5:I131="Cash")*('Sales Entry'!M5:M131)) | G29: =SUMPRODUCT(('Sales Entry'!B5:B131=B29)*('Sales Entry'!I5:I131="Card")*('Sales Entry'!M5:M131)) | H29: =SUMPRODUCT(('Sales Entry'!B5:B131=B29)*('Sales Entry'!I5:I131="Online")*('Sales Entry'!M5:M131)) | I29: =SUMPRODUCT(('Sales Entry'!B5:B131=B29)*('Sales Entry'!I5:I131="Bank Transfer")*('Sales Entry'!M5:M131)) | J29: =SUMPRODUCT(('Sales Entry'!B5:B131=B29)*('Sales Entry'!F5:F131)) | K29: =SUMPRODUCT(('Sales Entry'!B5:B131=B29)*('Sales Entry'!L5:L131))
B30: 45742 | C30: =SUMPRODUCT(('Sales Entry'!B5:B131=B30)*('Sales Entry'!M5:M131)) | D30: =SUMPRODUCT(('Sales Entry'!B5:B131=B30)*1) | E30: =IFERROR(C30/D30,0) | F30: =SUMPRODUCT(('Sales Entry'!B5:B131=B30)*('Sales Entry'!I5:I131="Cash")*('Sales Entry'!M5:M131)) | G30: =SUMPRODUCT(('Sales Entry'!B5:B131=B30)*('Sales Entry'!I5:I131="Card")*('Sales Entry'!M5:M131)) | H30: =SUMPRODUCT(('Sales Entry'!B5:B131=B30)*('Sales Entry'!I5:I131="Online")*('Sales Entry'!M5:M131)) | I30: =SUMPRODUCT(('Sales Entry'!B5:B131=B30)*('Sales Entry'!I5:I131="Bank Transfer")*('Sales Entry'!M5:M131)) | J30: =SUMPRODUCT(('Sales Entry'!B5:B131=B30)*('Sales Entry'!F5:F131)) | K30: =SUMPRODUCT(('Sales Entry'!B5:B131=B30)*('Sales Entry'!L5:L131))
B31: 45743 | C31: =SUMPRODUCT(('Sales Entry'!B5:B131=B31)*('Sales Entry'!M5:M131)) | D31: =SUMPRODUCT(('Sales Entry'!B5:B131=B31)*1) | E31: =IFERROR(C31/D31,0) | F31: =SUMPRODUCT(('Sales Entry'!B5:B131=B31)*('Sales Entry'!I5:I131="Cash")*('Sales Entry'!M5:M131)) | G31: =SUMPRODUCT(('Sales Entry'!B5:B131=B31)*('Sales Entry'!I5:I131="Card")*('Sales Entry'!M5:M131)) | H31: =SUMPRODUCT(('Sales Entry'!B5:B131=B31)*('Sales Entry'!I5:I131="Online")*('Sales Entry'!M5:M131)) | I31: =SUMPRODUCT(('Sales Entry'!B5:B131=B31)*('Sales Entry'!I5:I131="Bank Transfer")*('Sales Entry'!M5:M131)) | J31: =SUMPRODUCT(('Sales Entry'!B5:B131=B31)*('Sales Entry'!F5:F131)) | K31: =SUMPRODUCT(('Sales Entry'!B5:B131=B31)*('Sales Entry'!L5:L131))
B32: 45744 | C32: =SUMPRODUCT(('Sales Entry'!B5:B131=B32)*('Sales Entry'!M5:M131)) | D32: =SUMPRODUCT(('Sales Entry'!B5:B131=B32)*1) | E32: =IFERROR(C32/D32,0) | F32: =SUMPRODUCT(('Sales Entry'!B5:B131=B32)*('Sales Entry'!I5:I131="Cash")*('Sales Entry'!M5:M131)) | G32: =SUMPRODUCT(('Sales Entry'!B5:B131=B32)*('Sales Entry'!I5:I131="Card")*('Sales Entry'!M5:M131)) | H32: =SUMPRODUCT(('Sales Entry'!B5:B131=B32)*('Sales Entry'!I5:I131="Online")*('Sales Entry'!M5:M131)) | I32: =SUMPRODUCT(('Sales Entry'!B5:B131=B32)*('Sales Entry'!I5:I131="Bank Transfer")*('Sales Entry'!M5:M131)) | J32: =SUMPRODUCT(('Sales Entry'!B5:B131=B32)*('Sales Entry'!F5:F131)) | K32: =SUMPRODUCT(('Sales Entry'!B5:B131=B32)*('Sales Entry'!L5:L131))
B33: 45745 | C33: =SUMPRODUCT(('Sales Entry'!B5:B131=B33)*('Sales Entry'!M5:M131)) | D33: =SUMPRODUCT(('Sales Entry'!B5:B131=B33)*1) | E33: =IFERROR(C33/D33,0) | F33: =SUMPRODUCT(('Sales Entry'!B5:B131=B33)*('Sales Entry'!I5:I131="Cash")*('Sales Entry'!M5:M131)) | G33: =SUMPRODUCT(('Sales Entry'!B5:B131=B33)*('Sales Entry'!I5:I131="Card")*('Sales Entry'!M5:M131)) | H33: =SUMPRODUCT(('Sales Entry'!B5:B131=B33)*('Sales Entry'!I5:I131="Online")*('Sales Entry'!M5:M131)) | I33: =SUMPRODUCT(('Sales Entry'!B5:B131=B33)*('Sales Entry'!I5:I131="Bank Transfer")*('Sales Entry'!M5:M131)) | J33: =SUMPRODUCT(('Sales Entry'!B5:B131=B33)*('Sales Entry'!F5:F131)) | K33: =SUMPRODUCT(('Sales Entry'!B5:B131=B33)*('Sales Entry'!L5:L131))
B34: 45746 | C34: =SUMPRODUCT(('Sales Entry'!B5:B131=B34)*('Sales Entry'!M5:M131)) | D34: =SUMPRODUCT(('Sales Entry'!B5:B131=B34)*1) | E34: =IFERROR(C34/D34,0) | F34: =SUMPRODUCT(('Sales Entry'!B5:B131=B34)*('Sales Entry'!I5:I131="Cash")*('Sales Entry'!M5:M131)) | G34: =SUMPRODUCT(('Sales Entry'!B5:B131=B34)*('Sales Entry'!I5:I131="Card")*('Sales Entry'!M5:M131)) | H34: =SUMPRODUCT(('Sales Entry'!B5:B131=B34)*('Sales Entry'!I5:I131="Online")*('Sales Entry'!M5:M131)) | I34: =SUMPRODUCT(('Sales Entry'!B5:B131=B34)*('Sales Entry'!I5:I131="Bank Transfer")*('Sales Entry'!M5:M131)) | J34: =SUMPRODUCT(('Sales Entry'!B5:B131=B34)*('Sales Entry'!F5:F131)) | K34: =SUMPRODUCT(('Sales Entry'!B5:B131=B34)*('Sales Entry'!L5:L131))
B35: 45747 | C35: =SUMPRODUCT(('Sales Entry'!B5:B131=B35)*('Sales Entry'!M5:M131)) | D35: =SUMPRODUCT(('Sales Entry'!B5:B131=B35)*1) | E35: =IFERROR(C35/D35,0) | F35: =SUMPRODUCT(('Sales Entry'!B5:B131=B35)*('Sales Entry'!I5:I131="Cash")*('Sales Entry'!M5:M131)) | G35: =SUMPRODUCT(('Sales Entry'!B5:B131=B35)*('Sales Entry'!I5:I131="Card")*('Sales Entry'!M5:M131)) | H35: =SUMPRODUCT(('Sales Entry'!B5:B131=B35)*('Sales Entry'!I5:I131="Online")*('Sales Entry'!M5:M131)) | I35: =SUMPRODUCT(('Sales Entry'!B5:B131=B35)*('Sales Entry'!I5:I131="Bank Transfer")*('Sales Entry'!M5:M131)) | J35: =SUMPRODUCT(('Sales Entry'!B5:B131=B35)*('Sales Entry'!F5:F131)) | K35: =SUMPRODUCT(('Sales Entry'!B5:B131=B35)*('Sales Entry'!L5:L131))
B36: TOTALS | C36: =SUM(C5:C35) | D36: =SUM(D5:D35) | E36: =IFERROR(C36/D36,0) | F36: =SUM(F5:F35) | G36: =SUM(G5:G35) | H36: =SUM(H5:H35) | I36: =SUM(I5:I35) | J36: =SUM(J5:J35) | K36: =SUM(K5:K35)

Sheet Weekly Summary
B2: Weekly Summary — March 2025
B4: Week # | C4: Week Start | D4: Week End | E4: Total Sales | F4: # Transactions | G4: Avg Transaction | H4: Top Staff | I4: Profit Estimate
B5: 1 | C5: 45717 | D5: 45723 | E5: =SUM('Daily Summary'!C5:C11) | F5: =SUM('Daily Summary'!D5:D11) | G5: =IFERROR(E5/F5,0) | H5: Ahmed | I5: =E5*0.4
B6: 2 | C6: 45724 | D6: 45730 | E6: =SUM('Daily Summary'!C12:C18) | F6: =SUM('Daily Summary'!D12:D18) | G6: =IFERROR(E6/F6,0) | H6: Fatima | I6: =E6*0.4
B7: 3 | C7: 45731 | D7: 45737 | E7: =SUM('Daily Summary'!C19:C25) | F7: =SUM('Daily Summary'!D19:D25) | G7: =IFERROR(E7/F7,0) | H7: Sara | I7: =E7*0.4
B8: 4 | C8: 45738 | D8: 45744 | E8: =SUM('Daily Summary'!C26:C32) | F8: =SUM('Daily Summary'!D26:D32) | G8: =IFERROR(E8/F8,0) | H8: Khalid | I8: =E8*0.4
B9: 5 | C9: 45745 | D9: 45747 | E9: =SUM('Daily Summary'!C33:C35) | F9: =SUM('Daily Summary'!D33:D35) | G9: =IFERROR(E9/F9,0) | H9: Omar | I9: =E9*0.4
B10: TOTALS | E10: =SUM(E5:E9) | F10: =SUM(F5:F9) | G10: =IFERROR(E10/F10,0) | I10: =SUM(I5:I9)

Sheet Monthly Summary
B2: Monthly Summary — March 2025
B4: Month | C4: Total Sales | D4: # Transactions | E4: Avg Transaction | F4: Best Day Sales | G4: Best Day Date | H4: Total Expenses | I4: Net Profit
B5: March 2025 | C5: =SUM('Daily Summary'!C5:C35) | D5: =SUM('Daily Summary'!D5:D35) | E5: =IFERROR(C5/D5,0) | F5: =MAX('Daily Summary'!C5:C35) | G5: =INDEX('Daily Summary'!B5:B35,MATCH(E5,'Daily Summary'!C5:C35,0)) | H5: =SUM('Expenses'!E5:E44) | I5: =C5-G5
B6: TOTALS | C6: =SUM('Daily Summary'!C5:C35) | D6: =SUM('Daily Summary'!D5:D35) | E6: =IFERROR(C6/D6,0) | F6: =MAX('Daily Summary'!C5:C35) | H6: =SUM('Expenses'!E5:E44) | I6: =C5-G5
B9: Category | C9: Amount
B10: Total Sales | C10: =C5
B11: Total Expenses | C11: =G5
B12: Net Profit | C12: =H5

Sheet Invoice
B2: TechZone Electronics
B3: Premium Electronics & Accessories | Dubai, UAE
B5: INVOICE | E5: Invoice #: | F5: INV-0142
E6: Date: | F6: 45731
E7: Customer: | F7: Mohamed Al Rashid
E8: Staff: | F8: Fatima
B10: # | C10: Item | D10: Qty | E10: Unit Price | F10: Total
B11: 1 | C11: Tablet | D11: 1 | E11: 899 | F11: 899
B12: 2 | C12: Screen Protector | D12: 2 | E12: 30 | F12: 60
B13: 3 | C13: Earbuds | D13: 1 | E13: 85 | F13: 85
B14: 4 | C14: Phone Case | D14: 1 | E14: 45 | F14: 45
C15: Subtotal | F15: 1089
C16: Discount | F16: -50
C17: VAT (5%) | F17: 51.95
C19: GRAND TOTAL | F19: 1090.95
B21: Thank you for shopping at TechZone Electronics!
B22: Returns within 14 days with receipt. VAT Registration No: 100XXXXXX000003

Sheet Inventory
B2: Inventory — TechZone Electronics
B4: Product ID | C4: Item Name | D4: Category | E4: Unit Price | F4: Cost Price | G4: Margin | H4: Stock Qty | I4: Reorder Level | J4: Status | K4: Supplier | L4: Last Restocked | M4: Days Since Restock
B5: P001 | C5: Phone Case | D5: Accessories | E5: 45 | F5: 20 | G5: =IFERROR((E5-F5)/E5,0) | H5: 22 | I5: 15 | J5: =IF(H5<=I5,"LOW STOCK","In Stock") | K5: Samsung Gulf | L5: 45726 | M5: =MAX(0,TODAY()-L5)
B6: P002 | C6: USB Cable | D6: Accessories | E6: 25 | F6: 10 | G6: =IFERROR((E6-F6)/E6,0) | H6: 28 | I6: 20 | J6: =IF(H6<=I6,"LOW STOCK","In Stock") | K6: Accessories Plus | L6: 45724 | M6: =MAX(0,TODAY()-L6)
B7: P003 | C7: Screen Protector | D7: Accessories | E7: 30 | F7: 12 | G7: =IFERROR((E7-F7)/E7,0) | H7: 3 | I7: 15 | J7: =IF(H7<=I7,"LOW STOCK","In Stock") | K7: Apple ME | L7: 45728 | M7: =MAX(0,TODAY()-L7)
B8: P004 | C8: Power Bank | D8: Accessories | E8: 120 | F8: 55 | G8: =IFERROR((E8-F8)/E8,0) | H8: 12 | I8: 10 | J8: =IF(H8<=I8,"LOW STOCK","In Stock") | K8: Samsung Gulf | L8: 45721 | M8: =MAX(0,TODAY()-L8)
B9: P005 | C9: Earbuds | D9: Audio | E9: 85 | F9: 40 | G9: =IFERROR((E9-F9)/E9,0) | H9: 18 | I9: 12 | J9: =IF(H9<=I9,"LOW STOCK","In Stock") | K9: Apple ME | L9: 45731 | M9: =MAX(0,TODAY()-L9)
B10: P006 | C10: Bluetooth Speaker | D10: Audio | E10: 150 | F10: 70 | G10: =IFERROR((E10-F10)/E10,0) | H10: 14 | I10: 8 | J10: =IF(H10<=I10,"LOW STOCK","In Stock") | K10: Samsung Gulf | L10: 45717 | M10: =MAX(0,TODAY()-L10)
B11: P007 | C11: Headphones | D11: Audio | E11: 200 | F11: 90 | G11: =IFERROR((E11-F11)/E11,0) | H11: 2 | I11: 6 | J11: =IF(H11<=I11,"LOW STOCK","In Stock") | K11: Apple ME | L11: 45736 | M11: =MAX(0,TODAY()-L11)
B12: P008 | C12: Tablet | D12: Devices | E12: 899 | F12: 540 | G12: =IFERROR((E12-F12)/E12,0) | H12: 6 | I12: 3 | J12: =IF(H12<=I12,"LOW STOCK","In Stock") | K12: Apple ME | L12: 45734 | M12: =MAX(0,TODAY()-L12)
B13: P009 | C13: Smart Watch | D13: Wearables | E13: 450 | F13: 270 | G13: =IFERROR((E13-F13)/E13,0) | H13: 3 | I13: 5 | J13: =IF(H13<=I13,"LOW STOCK","In Stock") | K13: Apple ME | L13: 45730 | M13: =MAX(0,TODAY()-L13)
B14: P010 | C14: Fitness Band | D14: Wearables | E14: 180 | F14: 90 | G14: =IFERROR((E14-F14)/E14,0) | H14: 15 | I14: 8 | J14: =IF(H14<=I14,"LOW STOCK","In Stock") | K14: Samsung Gulf | L14: 45725 | M14: =MAX(0,TODAY()-L14)
B15: P011 | C15: Laptop Stand | D15: Accessories | E15: 150 | F15: 65 | G15: =IFERROR((E15-F15)/E15,0) | H15: 14 | I15: 10 | J15: =IF(H15<=I15,"LOW STOCK","In Stock") | K15: Dell Middle East | L15: 45723 | M15: =MAX(0,TODAY()-L15)
B16: P012 | C16: Keyboard | D16: Peripherals | E16: 200 | F16: 100 | G16: =IFERROR((E16-F16)/E16,0) | H16: 15 | I16: 8 | J16: =IF(H16<=I16,"LOW STOCK","In Stock") | K16: Dell Middle East | L16: 45727 | M16: =MAX(0,TODAY()-L16)
... B38: P034 | C38: Tripod Stand | D38: Accessories | E38: 90 | F38: 38 | G38: =IFERROR((E38-F38)/E38,0) | H38: 12 | I38: 8 | J38: =IF(H38<=I38,"LOW STOCK","In Stock") | K38: TechParts UAE | L38: 45729 | M38: =MAX(0,TODAY()-L38)
B39: TOTALS | H39: =SUM(H5:H38) | J39: =COUNTIF(J5:J38,"LOW STOCK")

Sheet Staff Performance
B2: Staff Performance — March 2025
B4: Staff Name | C4: Total Sales | D4: # Transactions | E4: Avg Transaction | F4: Top Category | G4: Shift | H4: Commission (5%) | I4: Sales Target | J4: Target Achievement %
B5: Ahmed | C5: =SUMPRODUCT(('Sales Entry'!J5:J131=B5)*('Sales Entry'!M5:M131)) | D5: =SUMPRODUCT(('Sales Entry'!J5:J131=B5)*1) | E5: =IFERROR(C5/D5,0) | F5: Accessories | G5: Morning | H5: =C5*0.05 | I5: 25000 | J5: =IFERROR(C5/I5,0)
B6: Fatima | C6: =SUMPRODUCT(('Sales Entry'!J5:J131=B6)*('Sales Entry'!M5:M131)) | D6: =SUMPRODUCT(('Sales Entry'!J5:J131=B6)*1) | E6: =IFERROR(C6/D6,0) | F6: Devices | G6: Afternoon | H6: =C6*0.05 | I6: 28000 | J6: =IFERROR(C6/I6,0)
B7: Omar | C7: =SUMPRODUCT(('Sales Entry'!J5:J131=B7)*('Sales Entry'!M5:M131)) | D7: =SUMPRODUCT(('Sales Entry'!J5:J131=B7)*1) | E7: =IFERROR(C7/D7,0) | F7: Audio | G7: Evening | H7: =C7*0.05 | I7: 22000 | J7: =IFERROR(C7/I7,0)
B8: Sara | C8: =SUMPRODUCT(('Sales Entry'!J5:J131=B8)*('Sales Entry'!M5:M131)) | D8: =SUMPRODUCT(('Sales Entry'!J5:J131=B8)*1) | E8: =IFERROR(C8/D8,0) | F8: Accessories | G8: Morning | H8: =C8*0.05 | I8: 26000 | J8: =IFERROR(C8/I8,0)
B9: Khalid | C9: =SUMPRODUCT(('Sales Entry'!J5:J131=B9)*('Sales Entry'!M5:M131)) | D9: =SUMPRODUCT(('Sales Entry'!J5:J131=B9)*1) | E9: =IFERROR(C9/D9,0) | F9: Peripherals | G9: Afternoon | H9: =C9*0.05 | I9: 20000 | J9: =IFERROR(C9/I9,0)
B10: Maryam | C10: =SUMPRODUCT(('Sales Entry'!J5:J131=B10)*('Sales Entry'!M5:M131)) | D10: =SUMPRODUCT(('Sales Entry'!J5:J131=B10)*1) | E10: =IFERROR(C10/D10,0) | F10: Wearables | G10: Morning | H10: =C10*0.05 | I10: 24000 | J10: =IFERROR(C10/I10,0)
B11: TOTALS | C11: =SUM(C5:C10) | D11: =SUM(D5:D10) | E11: =IFERROR(C11/D11,0) | H11: =SUM(H5:H10) | I11: =SUM(I5:I10) | J11: =IFERROR(C11/I11,0)

Sheet Expenses
B2: Expenses — March 2025
B4: Date | C4: Expense Category | D4: Description | E4: Amount | F4: Payment Method | G4: Vendor | H4: Receipt # | I4: Notes
B5: 45717 | C5: Rent | D5: Shop monthly rent - Dubai Mall | E5: 25000 | F5: Bank Transfer | G5: Emaar Properties | H5: RCP-3001 | I5: Fixed monthly
B6: 45717 | C6: Salaries | D6: Staff salaries - March | E6: 32000 | F6: Bank Transfer | G6: HR Payroll | H6: RCP-3002 | I6: 6 staff members
B7: 45717 | C7: Utilities | D7: DEWA electricity bill | E7: 3500 | F7: Bank Transfer | G7: DEWA | H7: RCP-3003 | I7: Feb consumption
B8: 45718 | C8: Utilities | D8: Water bill | E8: 450 | F8: Bank Transfer | G8: DEWA | H8: RCP-3004
B9: 45719 | C9: Supplies | D9: Thermal receipt paper rolls | E9: 280 | F9: Card | G9: Office Depot UAE | H9: RCP-3005 | I9: 20 rolls
B10: 45719 | C10: Supplies | D10: Shopping bags & packaging | E10: 650 | F10: Card | G10: PackPro UAE | H10: RCP-3006 | I10: Branded bags
B11: 45720 | C11: Maintenance | D11: POS system maintenance | E11: 500 | F11: Bank Transfer | G11: TechServ ME | H11: RCP-3007 | I11: Quarterly service
B12: 45721 | C12: Marketing | D12: Google Ads campaign | E12: 2000 | F12: Card | G12: Google Ireland | H12: RCP-3008 | I12: 2-week campaign
B13: 45721 | C13: Marketing | D13: Instagram sponsored posts | E13: 800 | F13: Card | G13: Meta Platforms | H13: RCP-3009
B14: 45722 | C14: Transport | D14: Delivery vehicle fuel | E14: 350 | F14: Cash | G14: ADNOC | H14: RCP-3010
B15: 45723 | C15: Supplies | D15: Display shelves & hooks | E15: 1200 | F15: Card | G15: ShopFittings UAE | H15: RCP-3011 | I15: New display units
B16: 45724 | C16: Insurance | D16: Shop insurance premium | E16: 1800 | F16: Bank Transfer | G16: Oman Insurance | H16: RCP-3012 | I16: Quarterly premium
B17: 45725 | C17: Maintenance | D17: AC maintenance service | E17: 600 | F17: Cash | G17: CoolTech Services | H17: RCP-3013 | I17: Filter replacement
B18: 45726 | C18: Transport | D18: Courier service - customer deliveries | E18: 450 | F18: Card | G18: Aramex | H18: RCP-3014 | I18: March deliveries
B19: 45727 | C19: Marketing | D19: Radio ad - Dubai Eye | E19: 1500 | F19: Bank Transfer | G19: Arabian Radio Network | H19: RCP-3015 | I19: 1-week spot
B20: 45728 | C20: Supplies | D20: Cleaning supplies | E20: 180 | F20: Cash | G20: Carrefour | H20: RCP-3016
B21: 45729 | C21: Miscellaneous | D21: Staff lunch - team meeting | E21: 350 | F21: Card | G21: Tim Hortons | H21: RCP-3017 | I21: Monthly meeting
B22: 45730 | C22: Utilities | D22: Internet & phone - Etisalat | E22: 900 | F22: Bank Transfer | G22: Etisalat | H22: RCP-3018 | I22: Business plan
B23: 45731 | C23: Salaries | D23: Overtime pay - March | E23: 2500 | F23: Bank Transfer | G23: HR Payroll | H23: RCP-3019 | I23: Weekend shifts
B24: 45732 | C24: Maintenance | D24: Security system check | E24: 400 | F24: Card | G24: SecureTech | H24: RCP-3020
B25: 45733 | C25: Marketing | D25: Ramadan promotion flyers | E25: 750 | F25: Cash | G25: PrintZone | H25: RCP-3021 | I25: 2000 flyers
B26: 45734 | C26: Transport | D26: Fuel - delivery vehicle | E26: 300 | F26: Cash | G26: ENOC | H26: RCP-3022
B27: 45735 | C27: Supplies | D27: Price tags & labels | E27: 150 | F27: Card | G27: LabelPro | H27: RCP-3023
B28: 45736 | C28: Miscellaneous | D28: Office coffee & tea supplies | E28: 200 | F28: Cash | G28: Carrefour | H28: RCP-3024
B29: 45737 | C29: Marketing | D29: Social media influencer | E29: 3000 | F29: Bank Transfer | G29: Influencer Hub | H29: RCP-3025 | I29: Product placement
B30: 45738 | C30: Maintenance | D30: Glass door repair | E30: 700 | F30: Cash | G30: GlassFix Dubai | H30: RCP-3026 | I30: Cracked panel
B31: 45739 | C31: Supplies | D31: Anti-theft security tags | E31: 450 | F31: Card | G31: SecureTag ME | H31: RCP-3027 | I31: 50 tags
B32: 45740 | C32: Insurance | D32: Inventory insurance | E32: 1200 | F32: Bank Transfer | G32: AXA Gulf | H32: RCP-3028 | I32: Quarterly
B33: 45741 | C33: Utilities | D33: DEWA electricity - mid month | E33: 2800 | F33: Bank Transfer | G33: DEWA | H33: RCP-3029 | I33: Adjusted reading
B34: 45742 | C34: Transport | D34: Courier - express deliveries | E34: 550 | F34: Card | G34: DHL Express | H34: RCP-3030 | I34: Priority orders
B35: 45743 | C35: Marketing | D35: Website hosting & SSL | E35: 400 | F35: Card | G35: GoDaddy | H35: RCP-3031 | I35: Annual renewal
B36: 45744 | C36: Miscellaneous | D36: Bank charges & fees | E36: 180 | F36: Bank Transfer | G36: Emirates NBD | H36: RCP-3032 | I36: Transaction fees
B37: 45744 | C37: Supplies | D37: Stationery & printer ink | E37: 320 | F37: Card | G37: Office Depot UAE | H37: RCP-3033
B38: 45745 | C38: Maintenance | D38: Fire extinguisher inspection | E38: 250 | F38: Cash | G38: SafeFire UAE | H38: RCP-3034 | I38: Annual check
B39: 45746 | C39: Miscellaneous | D39: Customer gift cards | E39: 500 | F39: Card | G39: GiftCardCo | H39: RCP-3035 | I39: Loyalty program
B40: 45746 | C40: Marketing | D40: Email marketing platform | E40: 250 | F40: Card | G40: Mailchimp | H40: RCP-3036 | I40: Monthly subscription
B41: 45747 | C41: Salaries | D41: End of month bonus | E41: 3000 | F41: Bank Transfer | G41: HR Payroll | H41: RCP-3037 | I41: Performance bonus
B42: 45747 | C42: Utilities | D42: District cooling - Empower | E42: 1200 | F42: Bank Transfer | G42: Empower | H42: RCP-3038 | I42: March billing
B43: 45747 | C43: Transport | D43: Monthly vehicle maintenance | E43: 800 | F43: Card | G43: AutoServ Dubai | H43: RCP-3039 | I43: Oil change & tires
B44: 45747 | C44: Miscellaneous | D44: Waste management fee | E44: 300 | F44: Bank Transfer | G44: Averda | H44: RCP-3040 | I44: Monthly collection
B45: TOTALS | E45: =SUM(E5:E44)
B47: Summary by Category
B48: Category | C48: Total Amount
B49: Rent | C49: =SUMPRODUCT((C5:C44=B49)*(E5:E44))
B50: Salaries | C50: =SUMPRODUCT((C5:C44=B50)*(E5:E44))
B51: Utilities | C51: =SUMPRODUCT((C5:C44=B51)*(E5:E44))
B52: Supplies | C52: =SUMPRODUCT((C5:C44=B52)*(E5:E44))
B53: Maintenance | C53: =SUMPRODUCT((C5:C44=B53)*(E5:E44))
B54: Marketing | C54: =SUMPRODUCT((C5:C44=B54)*(E5:E44))
B55: Transport | C55: =SUMPRODUCT((C5:C44=B55)*(E5:E44))
B56: Insurance | C56: =SUMPRODUCT((C5:C44=B56)*(E5:E44))
B57: Miscellaneous | C57: =SUMPRODUCT((C5:C44=B57)*(E5:E44))

Sheet Profit Analysis
B2: Profit & Loss Analysis — March 2025
B4: Item | C4: Amount (AED) | D4: % of Revenue | E4: Notes
B5: Revenue | C5: ='Monthly Summary'!C5 | E5: Total net sales for March
B6: Cost of Goods Sold (60%) | C6: =-C5*0.6 | E6: Estimated at 60% of revenue
B7: Gross Profit | C7: =C5+C6 | E7: Revenue minus COGS
B9: Operating Expenses | C9: ='Monthly Summary'!G5 | E9: Total from Expenses sheet
B11: Net Profit | C11: =C7-C9 | E11: Gross Profit minus Expenses
B12: Profit Margin % | C12: =IFERROR(C11/C5,0)
