Workbook

Sheet Daily Sales
B2: Daily Sales Record — [Month/Year]
B3: Enter daily data in the yellow-highlighted columns. All other columns calculate automatically.
B5: Day | C5: Date | D5: Walk-Ins | E5: Appointments | F5: Total Clients | G5: Service Revenue | H5: Product Revenue | I5: Total Revenue | J5: Cash | K5: Card | L5: Online | M5: Total Payments | N5: Payment Variance
B6: 1 | F6: =D6+E6 | I6: =G6+H6 | M6: =J6+K6+L6 | N6: =I6-M6
B7: 2 | F7: =D7+E7 | I7: =G7+H7 | M7: =J7+K7+L7 | N7: =I7-M7
B8: 3 | F8: =D8+E8 | I8: =G8+H8 | M8: =J8+K8+L8 | N8: =I8-M8
B9: 4 | F9: =D9+E9 | I9: =G9+H9 | M9: =J9+K9+L9 | N9: =I9-M9
B10: 5 | F10: =D10+E10 | I10: =G10+H10 | M10: =J10+K10+L10 | N10: =I10-M10
B11: 6 | F11: =D11+E11 | I11: =G11+H11 | M11: =J11+K11+L11 | N11: =I11-M11
B12: 7 | F12: =D12+E12 | I12: =G12+H12 | M12: =J12+K12+L12 | N12: =I12-M12
B13: 8 | F13: =D13+E13 | I13: =G13+H13 | M13: =J13+K13+L13 | N13: =I13-M13
B14: 9 | F14: =D14+E14 | I14: =G14+H14 | M14: =J14+K14+L14 | N14: =I14-M14
B15: 10 | F15: =D15+E15 | I15: =G15+H15 | M15: =J15+K15+L15 | N15: =I15-M15
B16: 11 | F16: =D16+E16 | I16: =G16+H16 | M16: =J16+K16+L16 | N16: =I16-M16
B17: 12 | F17: =D17+E17 | I17: =G17+H17 | M17: =J17+K17+L17 | N17: =I17-M17
... B36: 31 | F36: =D36+E36 | I36: =G36+H36 | M36: =J36+K36+L36 | N36: =I36-M36
B37: TOTAL | D37: =SUM(D6:D36) | E37: =SUM(E6:E36) | F37: =SUM(F6:F36) | G37: =SUM(G6:G36) | H37: =SUM(H6:H36) | I37: =SUM(I6:I36) | J37: =SUM(J6:J36) | K37: =SUM(K6:K36) | ... N37: =SUM(N6:N36)
B38: AVERAGE | D38: =AVERAGE(D6:D36) | E38: =AVERAGE(E6:E36) | F38: =AVERAGE(F6:F36) | G38: =AVERAGE(G6:G36) | H38: =AVERAGE(H6:H36) | I38: =AVERAGE(I6:I36) | J38: =AVERAGE(J6:J36) | K38: =AVERAGE(K6:K36) | ... N38: =AVERAGE(N6:N36)
B39: BEST DAY | D39: =MAX(D6:D36) | E39: =MAX(E6:E36) | F39: =MAX(F6:F36) | G39: =MAX(G6:G36) | H39: =MAX(H6:H36) | I39: =MAX(I6:I36) | J39: =MAX(J6:J36) | K39: =MAX(K6:K36) | ... N39: =MAX(N6:N36)
B59: Prepared by Ahmed Ali | Data Analysis Services | ahmed-ali-ops.vercel.app

Sheet Service Breakdown
B2: Service Revenue Breakdown — [Month/Year]
B4: Service | C4: Bookings | D4: Avg Price (AED) | E4: Revenue | F4: % of Total | G4: Target | H4: vs Target
B5: Haircut & Styling | E5: =C5*D5 | F5: =IFERROR(E5/SUM(E$5:E$16),0) | H5: =E5-G5
B6: Hair Coloring | E6: =C6*D6 | F6: =IFERROR(E6/SUM(E$5:E$16),0) | H6: =E6-G6
B7: Highlights & Balayage | E7: =C7*D7 | F7: =IFERROR(E7/SUM(E$5:E$16),0) | H7: =E7-G7
B8: Keratin Treatment | E8: =C8*D8 | F8: =IFERROR(E8/SUM(E$5:E$16),0) | H8: =E8-G8
B9: Bridal Package | E9: =C9*D9 | F9: =IFERROR(E9/SUM(E$5:E$16),0) | H9: =E9-G9
B10: Facial Treatment | E10: =C10*D10 | F10: =IFERROR(E10/SUM(E$5:E$16),0) | H10: =E10-G10
B11: Manicure & Pedicure | E11: =C11*D11 | F11: =IFERROR(E11/SUM(E$5:E$16),0) | H11: =E11-G11
B12: Henna Design | E12: =C12*D12 | F12: =IFERROR(E12/SUM(E$5:E$16),0) | H12: =E12-G12
B13: Hair Extensions | E13: =C13*D13 | F13: =IFERROR(E13/SUM(E$5:E$16),0) | H13: =E13-G13
B14: Scalp Treatment | E14: =C14*D14 | F14: =IFERROR(E14/SUM(E$5:E$16),0) | H14: =E14-G14
B15: Makeup | E15: =C15*D15 | F15: =IFERROR(E15/SUM(E$5:E$16),0) | H15: =E15-G15
B16: Other | E16: =C16*D16 | F16: =IFERROR(E16/SUM(E$5:E$16),0) | H16: =E16-G16
B17: TOTAL | C17: =SUM(C5:C16) | D17: — | E17: =SUM(E5:E16) | F17: =SUM(F5:F16) | G17: =SUM(G5:G16) | H17: =SUM(H5:H16)
B51: Prepared by Ahmed Ali | Data Analysis Services | ahmed-ali-ops.vercel.app

Sheet Staff Performance
B2: Staff Performance — [Month/Year]
B4: Staff Name | C4: Clients Served | D4: Revenue Generated | E4: Avg Ticket | F4: Tips | G4: Rating (1-5)
E5: =IFERROR(D5/C5,0)
E6: =IFERROR(D6/C6,0)
E7: =IFERROR(D7/C7,0)
E8: =IFERROR(D8/C8,0)
E9: =IFERROR(D9/C9,0)
E10: =IFERROR(D10/C10,0)
E11: =IFERROR(D11/C11,0)
E12: =IFERROR(D12/C12,0)
B13: TOTAL | C13: =SUM(C5:C12) | D13: =SUM(D5:D12) | E13: =IFERROR(D13/C13,0) | F13: =SUM(F5:F12) | G13: =AVERAGE(G5:G12)
B14: AVERAGE | C14: =AVERAGE(C5:C12) | D14: =AVERAGE(D5:D12) | E14: =AVERAGE(E5:E12) | F14: =AVERAGE(F5:F12) | G14: =AVERAGE(G5:G12)
B30: Prepared by Ahmed Ali | Data Analysis Services | ahmed-ali-ops.vercel.app

Sheet Expense Tracker
B2: Monthly Expenses — [Month/Year]
B4: Category | C4: Budget (AED) | D4: Actual (AED) | E4: Variance | F4: Variance % | G4: Status
B5: Rent | E5: =C5-D5 | F5: =IFERROR(E5/C5,0) | G5: =IF(E5<0,"Over Budget",IF(E5=0,"On Budget","Under Budget"))
B6: Staff Salaries | E6: =C6-D6 | F6: =IFERROR(E6/C6,0) | G6: =IF(E6<0,"Over Budget",IF(E6=0,"On Budget","Under Budget"))
B7: Product Supplies | E7: =C7-D7 | F7: =IFERROR(E7/C7,0) | G7: =IF(E7<0,"Over Budget",IF(E7=0,"On Budget","Under Budget"))
B8: Utilities | E8: =C8-D8 | F8: =IFERROR(E8/C8,0) | G8: =IF(E8<0,"Over Budget",IF(E8=0,"On Budget","Under Budget"))
B9: Marketing | E9: =C9-D9 | F9: =IFERROR(E9/C9,0) | G9: =IF(E9<0,"Over Budget",IF(E9=0,"On Budget","Under Budget"))
B10: Insurance | E10: =C10-D10 | F10: =IFERROR(E10/C10,0) | G10: =IF(E10<0,"Over Budget",IF(E10=0,"On Budget","Under Budget"))
B11: Maintenance | E11: =C11-D11 | F11: =IFERROR(E11/C11,0) | G11: =IF(E11<0,"Over Budget",IF(E11=0,"On Budget","Under Budget"))
B12: POS/Banking Fees | E12: =C12-D12 | F12: =IFERROR(E12/C12,0) | G12: =IF(E12<0,"Over Budget",IF(E12=0,"On Budget","Under Budget"))
B13: Delivery Commissions | E13: =C13-D13 | F13: =IFERROR(E13/C13,0) | G13: =IF(E13<0,"Over Budget",IF(E13=0,"On Budget","Under Budget"))
B14: Licenses & Permits | E14: =C14-D14 | F14: =IFERROR(E14/C14,0) | G14: =IF(E14<0,"Over Budget",IF(E14=0,"On Budget","Under Budget"))
B15: Miscellaneous | E15: =C15-D15 | F15: =IFERROR(E15/C15,0) | G15: =IF(E15<0,"Over Budget",IF(E15=0,"On Budget","Under Budget"))
B16: TOTAL | C16: =SUM(C5:C15) | D16: =SUM(D5:D15) | E16: =SUM(E5:E15) | F16: =IFERROR(E16/C16,0) | G16: —
B34: Prepared by Ahmed Ali | Data Analysis Services | ahmed-ali-ops.vercel.app

Sheet Monthly Summary
B2: Monthly Summary — [Month/Year]
B4: Metric | C4: Value
B5: Total Revenue | C5: ='Daily Sales'!I37
B6: Total Expenses | C6: ='Expense Tracker'!D16
B7: Net Profit | C7: =C5-C6
B8: Profit Margin | C8: =IFERROR(C7/C5,0)
B9: Total Clients | C9: ='Daily Sales'!F37
B10: Avg Revenue per Client | C10: =IFERROR(C5/C9,0)
B11: Best Day Revenue | C11: =MAX('Daily Sales'!I6:I36)
B12: Payment Variance | C12: ='Daily Sales'!N37
B13: Top Service | C13: ="See Service Breakdown"
B14: Staff Count | C14: =COUNTA('Staff Performance'!B5:B12)
B15: Avg Staff Revenue | C15: =IFERROR(C5/C14,0)
B17: 6-Month Comparison
B18: Month | C18: Revenue | D18: Expenses | E18: Profit | F18: Margin
B40: Prepared by Ahmed Ali | Data Analysis Services | ahmed-ali-ops.vercel.app

Sheet Instructions
B2: How to Use This Template
B4: 1. | C4: Go to "Daily Sales" sheet — enter your daily numbers in the yellow cells
B5: 2. | C5: Go to "Service Breakdown" — enter bookings and average prices for each service
B6: 3. | C6: Go to "Staff Performance" — enter each staff member's data
B7: 4. | C7: Go to "Expense Tracker" — enter your budget and actual expenses
B8: 5. | C8: The "Monthly Summary" updates automatically!
B9: 6. | C9: Yellow cells = YOU fill in. White cells = AUTO-CALCULATED.
B11: Need help? Contact Ahmed Ali | Data Analysis Services | ahmed-ali-ops.vercel.app
B13: Prepared by Ahmed Ali | Data Analysis Services | ahmed-ali-ops.vercel.app
